<ceg id="0109884774">
<rovat id = "0">
<alrovat id = "1">
<mezo id = "bir">01</mezo>
<mezo id = "cf">09</mezo>
<mezo id = "szam">884774</mezo>
<mezo id = "nevalrovat">1</mezo>
<mezo id = "cim">1239 Budapest, Láva utca 21. </mezo>
<mezo id = "plus">10</mezo>
<mezo id = "adosz">14013696243</mezo>
</alrovat>
</rovat>
<rovat id = "2">
<alrovat id = "1">
<mezo id = "hattol">20070810</mezo>
<mezo id = "nev">REÁL-GÉP Daru és Elektro Szervíz Korlátolt Felelősségű Társaság</mezo>
<mezo id = "valtk">0</mezo>
<mezo id = "valtv">0</mezo>
</alrovat>
</rovat>
<rovat id = "3">
<alrovat id = "1">
<mezo id = "hattol">20070810</mezo>
<mezo id = "nev">REÁL-GÉP Kft.</mezo>
<mezo id = "valtk">0</mezo>
<mezo id = "valtv">0</mezo>
</alrovat>
</rovat>
<rovat id = "5">
<alrovat id = "1">
<mezo id = "hattol">20070810</mezo>
<mezo id = "irsz">1239</mezo>
<mezo id = "hely">Budapest</mezo>
<mezo id = "teru">Láva utca 21.</mezo>
<mezo id = "kirsz">0</mezo>
<mezo id = "valtk">0</mezo>
<mezo id = "valtv">0</mezo>
</alrovat>
</rovat>
<rovat id = "8">
<alrovat id = "1">
<mezo id = "datum">20070801</mezo>
</alrovat>
<alrovat id = "2">
<mezo id = "datum">20080522</mezo>
<mezo id = "valtk">0</mezo>
<mezo id = "valtv">0</mezo>
<mezo id = "bkelt">0</mezo>
<mezo id = "tkelt">0</mezo>
</alrovat>
<alrovat id = "3">
<mezo id = "datum">20100924</mezo>
</alrovat>
</rovat>
<rovat id = "902">
<alrovat id = "12">
<mezo id = "hattol">20080522</mezo>
<mezo id = "fotev">x</mezo>
<mezo id = "hengk1">0</mezo>
<mezo id = "hengv1">0</mezo>
<mezo id = "hengk2">0</mezo>
<mezo id = "hengv2">0</mezo>
<mezo id = "hengk3">0</mezo>
<mezo id = "hengv3">0</mezo>
<mezo id = "hengk4">0</mezo>
<mezo id = "hengv4">0</mezo>
<mezo id = "korlk">0</mezo>
<mezo id = "korlv">0</mezo>
<mezo id = "valtk">20080522</mezo>
<mezo id = "valtv">0</mezo>
<mezo id = "bkelt">20080602</mezo>
<mezo id = "tkelt">0</mezo>
<mezo id = "tea08">2822</mezo>
</alrovat>
<alrovat id = "13">
<mezo id = "hattol">20080522</mezo>
<mezo id = "hengk1">0</mezo>
<mezo id = "hengv1">0</mezo>
<mezo id = "hengk2">0</mezo>
<mezo id = "hengv2">0</mezo>
<mezo id = "hengk3">0</mezo>
<mezo id = "hengv3">0</mezo>
<mezo id = "hengk4">0</mezo>
<mezo id = "hengv4">0</mezo>
<mezo id = "korlk">0</mezo>
<mezo id = "korlv">0</mezo>
<mezo id = "valtk">20080522</mezo>
<mezo id = "valtv">0</mezo>
<mezo id = "bkelt">20080602</mezo>
<mezo id = "tkelt">0</mezo>
<mezo id = "tea08">2511</mezo>
</alrovat>
<alrovat id = "14">
<mezo id = "hattol">20080522</mezo>
<mezo id = "hengk1">0</mezo>
<mezo id = "hengv1">0</mezo>
<mezo id = "hengk2">0</mezo>
<mezo id = "hengv2">0</mezo>
<mezo id = "hengk3">0</mezo>
<mezo id = "hengv3">0</mezo>
<mezo id = "hengk4">0</mezo>
<mezo id = "hengv4">0</mezo>
<mezo id = "korlk">0</mezo>
<mezo id = "korlv">0</mezo>
<mezo id = "valtk">20080522</mezo>
<mezo id = "valtv">0</mezo>
<mezo id = "bkelt">20080602</mezo>
<mezo id = "tkelt">0</mezo>
<mezo id = "tea08">2562</mezo>
</alrovat>
<alrovat id = "15">
<mezo id = "hattol">20080522</mezo>
<mezo id = "hengk1">0</mezo>
<mezo id = "hengv1">0</mezo>
<mezo id = "hengk2">0</mezo>
<mezo id = "hengv2">0</mezo>
<mezo id = "hengk3">0</mezo>
<mezo id = "hengv3">0</mezo>
<mezo id = "hengk4">0</mezo>
<mezo id = "hengv4">0</mezo>
<mezo id = "korlk">0</mezo>
<mezo id = "korlv">0</mezo>
<mezo id = "valtk">20080522</mezo>
<mezo id = "valtv">0</mezo>
<mezo id = "bkelt">20080602</mezo>
<mezo id = "tkelt">0</mezo>
<mezo id = "tea08">3312</mezo>
</alrovat>
<alrovat id = "16">
<mezo id = "hattol">20080522</mezo>
<mezo id = "hengk1">0</mezo>
<mezo id = "hengv1">0</mezo>
<mezo id = "hengk2">0</mezo>
<mezo id = "hengv2">0</mezo>
<mezo id = "hengk3">0</mezo>
<mezo id = "hengv3">0</mezo>
<mezo id = "hengk4">0</mezo>
<mezo id = "hengv4">0</mezo>
<mezo id = "korlk">0</mezo>
<mezo id = "korlv">0</mezo>
<mezo id = "valtk">20080522</mezo>
<mezo id = "valtv">0</mezo>
<mezo id = "bkelt">20080602</mezo>
<mezo id = "tkelt">0</mezo>
<mezo id = "tea08">3320</mezo>
</alrovat>
<alrovat id = "17">
<mezo id = "hattol">20080522</mezo>
<mezo id = "hengk1">0</mezo>
<mezo id = "hengv1">0</mezo>
<mezo id = "hengk2">0</mezo>
<mezo id = "hengv2">0</mezo>
<mezo id = "hengk3">0</mezo>
<mezo id = "hengv3">0</mezo>
<mezo id = "hengk4">0</mezo>
<mezo id = "hengv4">0</mezo>
<mezo id = "korlk">0</mezo>
<mezo id = "korlv">0</mezo>
<mezo id = "valtk">20080522</mezo>
<mezo id = "valtv">0</mezo>
<mezo id = "bkelt">20080602</mezo>
<mezo id = "tkelt">0</mezo>
<mezo id = "tea08">4120</mezo>
</alrovat>
<alrovat id = "18">
<mezo id = "hattol">20080522</mezo>
<mezo id = "hengk1">0</mezo>
<mezo id = "hengv1">0</mezo>
<mezo id = "hengk2">0</mezo>
<mezo id = "hengv2">0</mezo>
<mezo id = "hengk3">0</mezo>
<mezo id = "hengv3">0</mezo>
<mezo id = "hengk4">0</mezo>
<mezo id = "hengv4">0</mezo>
<mezo id = "korlk">0</mezo>
<mezo id = "korlv">0</mezo>
<mezo id = "valtk">20080522</mezo>
<mezo id = "valtv">0</mezo>
<mezo id = "bkelt">20080602</mezo>
<mezo id = "tkelt">0</mezo>
<mezo id = "tea08">4321</mezo>
</alrovat>
<alrovat id = "19">
<mezo id = "hattol">20080522</mezo>
<mezo id = "hengk1">0</mezo>
<mezo id = "hengv1">0</mezo>
<mezo id = "hengk2">0</mezo>
<mezo id = "hengv2">0</mezo>
<mezo id = "hengk3">0</mezo>
<mezo id = "hengv3">0</mezo>
<mezo id = "hengk4">0</mezo>
<mezo id = "hengv4">0</mezo>
<mezo id = "korlk">0</mezo>
<mezo id = "korlv">0</mezo>
<mezo id = "valtk">20080522</mezo>
<mezo id = "valtv">0</mezo>
<mezo id = "bkelt">20080602</mezo>
<mezo id = "tkelt">0</mezo>
<mezo id = "tea08">4322</mezo>
</alrovat>
<alrovat id = "20">
<mezo id = "hattol">20080522</mezo>
<mezo id = "hengk1">0</mezo>
<mezo id = "hengv1">0</mezo>
<mezo id = "hengk2">0</mezo>
<mezo id = "hengv2">0</mezo>
<mezo id = "hengk3">0</mezo>
<mezo id = "hengv3">0</mezo>
<mezo id = "hengk4">0</mezo>
<mezo id = "hengv4">0</mezo>
<mezo id = "korlk">0</mezo>
<mezo id = "korlv">0</mezo>
<mezo id = "valtk">20080522</mezo>
<mezo id = "valtv">0</mezo>
<mezo id = "bkelt">20080602</mezo>
<mezo id = "tkelt">0</mezo>
<mezo id = "tea08">4329</mezo>
</alrovat>
<alrovat id = "21">
<mezo id = "hattol">20080522</mezo>
<mezo id = "hengk1">0</mezo>
<mezo id = "hengv1">0</mezo>
<mezo id = "hengk2">0</mezo>
<mezo id = "hengv2">0</mezo>
<mezo id = "hengk3">0</mezo>
<mezo id = "hengv3">0</mezo>
<mezo id = "hengk4">0</mezo>
<mezo id = "hengv4">0</mezo>
<mezo id = "korlk">0</mezo>
<mezo id = "korlv">0</mezo>
<mezo id = "valtk">20080522</mezo>
<mezo id = "valtv">0</mezo>
<mezo id = "bkelt">20080602</mezo>
<mezo id = "tkelt">0</mezo>
<mezo id = "tea08">4339</mezo>
</alrovat>
<alrovat id = "22">
<mezo id = "hattol">20080522</mezo>
<mezo id = "hengk1">0</mezo>
<mezo id = "hengv1">0</mezo>
<mezo id = "hengk2">0</mezo>
<mezo id = "hengv2">0</mezo>
<mezo id = "hengk3">0</mezo>
<mezo id = "hengv3">0</mezo>
<mezo id = "hengk4">0</mezo>
<mezo id = "hengv4">0</mezo>
<mezo id = "korlk">0</mezo>
<mezo id = "korlv">0</mezo>
<mezo id = "valtk">20080522</mezo>
<mezo id = "valtv">0</mezo>
<mezo id = "bkelt">20080602</mezo>
<mezo id = "tkelt">0</mezo>
<mezo id = "tea08">4399</mezo>
</alrovat>
<alrovat id = "23">
<mezo id = "hattol">20080522</mezo>
<mezo id = "hengk1">0</mezo>
<mezo id = "hengv1">0</mezo>
<mezo id = "hengk2">0</mezo>
<mezo id = "hengv2">0</mezo>
<mezo id = "hengk3">0</mezo>
<mezo id = "hengv3">0</mezo>
<mezo id = "hengk4">0</mezo>
<mezo id = "hengv4">0</mezo>
<mezo id = "korlk">0</mezo>
<mezo id = "korlv">0</mezo>
<mezo id = "valtk">20080522</mezo>
<mezo id = "valtv">0</mezo>
<mezo id = "bkelt">20080602</mezo>
<mezo id = "tkelt">0</mezo>
<mezo id = "tea08">7112</mezo>
</alrovat>
<alrovat id = "24">
<mezo id = "hattol">20080522</mezo>
<mezo id = "hengk1">0</mezo>
<mezo id = "hengv1">0</mezo>
<mezo id = "hengk2">0</mezo>
<mezo id = "hengv2">0</mezo>
<mezo id = "hengk3">0</mezo>
<mezo id = "hengv3">0</mezo>
<mezo id = "hengk4">0</mezo>
<mezo id = "hengv4">0</mezo>
<mezo id = "korlk">0</mezo>
<mezo id = "korlv">0</mezo>
<mezo id = "valtk">20080522</mezo>
<mezo id = "valtv">0</mezo>
<mezo id = "bkelt">20080602</mezo>
<mezo id = "tkelt">0</mezo>
<mezo id = "tea08">8299</mezo>
</alrovat>
</rovat>
<rovat id = "11">
<alrovat id = "2">
<mezo id = "hattol">20100929</mezo>
<mezo id = "kp">0</mezo>
<mezo id = "app">0</mezo>
<mezo id = "szam">20000000</mezo>
<mezo id = "penz">HUF</mezo>
<mezo id = "valtk">20100929</mezo>
<mezo id = "bkelt">20100929</mezo>
</alrovat>
</rovat>
<rovat id = "13">
<alrovat id = "2">
<mezo id = "hattol">20100924</mezo>
<mezo id = "tiszt">vezető tisztségviselő (ügyvezető)</mezo>
<mezo id = "pnev">Dalmady Balázs</mezo>
<mezo id = "panev">Koháry-Szabó Katalin</mezo>
<mezo id = "kepvo">x</mezo>
<mezo id = "jogvk">20100924</mezo>
<mezo id = "valtk">20100924</mezo>
<mezo id = "bkelt">20100929</mezo>
<mezo id = "adoazon">8407903523</mezo>
</alrovat>
<alrovat id = "3">
<mezo id = "hattol">20100929</mezo>
<mezo id = "tiszt">vezető tisztségviselő (ügyvezető)</mezo>
<mezo id = "pnev">Dalmady Antal Tamás</mezo>
<mezo id = "panev">Zsédely Mária</mezo>
<mezo id = "kepvo">x</mezo>
<mezo id = "jogvk">20070801</mezo>
<mezo id = "valtk">20100929</mezo>
<mezo id = "bkelt">20100929</mezo>
<mezo id = "adoazon">8313772573</mezo>
</alrovat>
</rovat>
<rovat id = "14">
<alrovat id = "1">
<mezo id = "hattol">20080522</mezo>
<mezo id = "cgjsz">109567551</mezo>
<mezo id = "nev">Giday és Fenesi Könyvvizsgáló Korlátolt Felelősségű Társaság</mezo>
<mezo id = "orsz">HU</mezo>
<mezo id = "irsz">1137</mezo>
<mezo id = "hely">Budapest</mezo>
<mezo id = "teru">Katona József utca</mezo>
<mezo id = "hsz">16.</mezo>
<mezo id = "pnev">dr. Giday Gabriella</mezo>
<mezo id = "panev">Paniti Gáspár Gabriella</mezo>
<mezo id = "pirsz">1137</mezo>
<mezo id = "phely">Budapest, Katona József u. 16.</mezo>
<mezo id = "jogvk">20080522</mezo>
<mezo id = "jogvv">20130522</mezo>
<mezo id = "valtk">20080522</mezo>
<mezo id = "valtv">0</mezo>
<mezo id = "bkelt">20080602</mezo>
<mezo id = "tkelt">0</mezo>
</alrovat>
</rovat>
<rovat id = "20">
<alrovat id = "1">
<mezo id = "hattol">20070810</mezo>
<mezo id = "kshsz">14013696292211301</mezo>
</alrovat>
</rovat>
<rovat id = "21">
<alrovat id = "1">
<mezo id = "hattol">20070810</mezo>
<mezo id = "adosz">14013696243</mezo>
<mezo id = "kadosz">HU14013696</mezo>
<mezo id = "nydat">20070806</mezo>
<mezo id = "fkdat">0</mezo>
<mezo id = "fmdat">0</mezo>
<mezo id = "jtdat">0</mezo>
<mezo id = "hmdat">0</mezo>
<mezo id = "hkdat">0</mezo>
</alrovat>
</rovat>
<rovat id = "0109">
<alrovat id = "1">
<mezo id = "hattol">20070810</mezo>
<mezo id = "cgjsz">109672934</mezo>
<mezo id = "nev">INVEST-STEEL Acélszerkezeti, Építési és Vasúti Jármű Beruházások Management Kft.</mezo>
<mezo id = "orsz">HU</mezo>
<mezo id = "irsz">1239</mezo>
<mezo id = "hely">Budapest</mezo>
<mezo id = "teru">Láva utca</mezo>
<mezo id = "hsz">21.</mezo>
<mezo id = "tagsk">20070801</mezo>
<mezo id = "tagsv">0</mezo>
<mezo id = "valtk">0</mezo>
<mezo id = "valtv">0</mezo>
</alrovat>
<alrovat id = "4">
<mezo id = "hattol">20100920</mezo>
<mezo id = "pnev">Dalmady Tamás</mezo>
<mezo id = "panev">Koháry-Szabó Katalin</mezo>
<mezo id = "tagsk">20100920</mezo>
<mezo id = "valtk">20100920</mezo>
<mezo id = "bkelt">20100929</mezo>
</alrovat>
<alrovat id = "5">
<mezo id = "hattol">20100920</mezo>
<mezo id = "pnev">Dalmady Balázs</mezo>
<mezo id = "panev">Koháry-Szabó Katalin</mezo>
<mezo id = "tagsk">20100920</mezo>
<mezo id = "valtk">20100920</mezo>
<mezo id = "bkelt">20100929</mezo>
</alrovat>
</rovat>
<rovat id = "99017">
<alrovat id = "1">
<mezo id = "kezd">20080101</mezo>
<mezo id = "veg">20081231</mezo>
<mezo id = "szorzo">1000</mezo>
<mezo id = "penz">HUF</mezo>
<mezo id = "a_eredm">40962</mezo>
<mezo id = "aktiv_el">0</mezo>
<mezo id = "eszk">7633</mezo>
<mezo id = "celtart">0</mezo>
<mezo id = "netto">324044</mezo>
<mezo id = "forgo">65537</mezo>
<mezo id = "kotelez">25543</mezo>
<mezo id = "m_eredm">15505</mezo>
<mezo id = "passziv_el">0</mezo>
<mezo id = "toke">47627</mezo>
<mezo id = "u_eredm">44547</mezo>
</alrovat>
<alrovat id = "2">
<mezo id = "kezd">20070801</mezo>
<mezo id = "veg">20070810</mezo>
<mezo id = "szorzo">1000</mezo>
<mezo id = "penz">HUF</mezo>
<mezo id = "a_eredm">-214</mezo>
<mezo id = "aktiv_el">0</mezo>
<mezo id = "eszk">0</mezo>
<mezo id = "celtart">0</mezo>
<mezo id = "netto">0</mezo>
<mezo id = "forgo">9882</mezo>
<mezo id = "kotelez">96</mezo>
<mezo id = "m_eredm">-214</mezo>
<mezo id = "passziv_el">0</mezo>
<mezo id = "toke">9786</mezo>
<mezo id = "u_eredm">-214</mezo>
</alrovat>
<alrovat id = "3">
<mezo id = "kezd">20070811</mezo>
<mezo id = "veg">20071231</mezo>
<mezo id = "szorzo">1000</mezo>
<mezo id = "penz">HUF</mezo>
<mezo id = "a_eredm">2662</mezo>
<mezo id = "aktiv_el">0</mezo>
<mezo id = "eszk">3568</mezo>
<mezo id = "celtart">0</mezo>
<mezo id = "netto">86878</mezo>
<mezo id = "forgo">34204</mezo>
<mezo id = "kotelez">25650</mezo>
<mezo id = "m_eredm">2336</mezo>
<mezo id = "passziv_el">0</mezo>
<mezo id = "toke">12122</mezo>
<mezo id = "u_eredm">2391</mezo>
</alrovat>
<alrovat id = "4">
<mezo id = "kezd">20090101</mezo>
<mezo id = "veg">20091231</mezo>
<mezo id = "szorzo">1000</mezo>
<mezo id = "penz">HUF</mezo>
<mezo id = "a_eredm">4168</mezo>
<mezo id = "aktiv_el">0</mezo>
<mezo id = "eszk">6210</mezo>
<mezo id = "celtart">0</mezo>
<mezo id = "netto">105394</mezo>
<mezo id = "forgo">48613</mezo>
<mezo id = "kotelez">13543</mezo>
<mezo id = "m_eredm">3653</mezo>
<mezo id = "passziv_el">0</mezo>
<mezo id = "toke">41280</mezo>
<mezo id = "u_eredm">645</mezo>
</alrovat>
<alrovat id = "5">
<mezo id = "kezd">20100101</mezo>
<mezo id = "veg">20101231</mezo>
<mezo id = "szorzo">1000</mezo>
<mezo id = "penz">HUF</mezo>
<mezo id = "a_eredm">1939</mezo>
<mezo id = "aktiv_el">20</mezo>
<mezo id = "eszk">16166</mezo>
<mezo id = "celtart">0</mezo>
<mezo id = "netto">113663</mezo>
<mezo id = "forgo">36463</mezo>
<mezo id = "kotelez">9730</mezo>
<mezo id = "m_eredm">1639</mezo>
<mezo id = "passziv_el">0</mezo>
<mezo id = "toke">42919</mezo>
<mezo id = "u_eredm">1354</mezo>
</alrovat>
</rovat>
</ceg>
