<ceg id="1509066727">
<rovat id = "0">
<alrovat id = "1">
<mezo id = "bir">15</mezo>
<mezo id = "cf">09</mezo>
<mezo id = "szam">066727</mezo>
<mezo id = "nevalrovat">4</mezo>
<mezo id = "cim">4400 Nyíregyháza, Deák Ferenc u. 21. </mezo>
<mezo id = "plus">10</mezo>
<mezo id = "adosz">12592751215</mezo>
</alrovat>
</rovat>
<rovat id = "2">
<alrovat id = "4">
<mezo id = "hattol">20100410</mezo>
<mezo id = "nev">Nyír-Mosaic Media Kereskedelmi és Szolgáltató Korlátolt Felelősségű Társaság</mezo>
<mezo id = "valtk">20100410</mezo>
<mezo id = "bkelt">20100504</mezo>
</alrovat>
</rovat>
<rovat id = "3">
<alrovat id = "4">
<mezo id = "hattol">20100410</mezo>
<mezo id = "nev">Nyír-Mosaic Media Kft.</mezo>
<mezo id = "valtk">20100410</mezo>
<mezo id = "bkelt">20100504</mezo>
</alrovat>
</rovat>
<rovat id = "5">
<alrovat id = "1">
<mezo id = "irsz">4400</mezo>
<mezo id = "hely">Nyíregyháza</mezo>
<mezo id = "teru">Szőlő</mezo>
<mezo id = "terj">u.</mezo>
<mezo id = "hsz">20/B</mezo>
</alrovat>
<alrovat id = "5">
<mezo id = "hattol">20071101</mezo>
<mezo id = "irsz">4400</mezo>
<mezo id = "hely">Nyíregyháza</mezo>
<mezo id = "teru">Deák Ferenc u. 21.</mezo>
<mezo id = "kirsz">0</mezo>
<mezo id = "valtk">20071101</mezo>
<mezo id = "valtv">0</mezo>
<mezo id = "bkelt">20071213</mezo>
<mezo id = "tkelt">0</mezo>
</alrovat>
</rovat>
<rovat id = "8">
<alrovat id = "1">
<mezo id = "datum">20010112</mezo>
</alrovat>
<alrovat id = "2">
<mezo id = "datum">20030310</mezo>
</alrovat>
<alrovat id = "3">
<mezo id = "datum">20060424</mezo>
</alrovat>
<alrovat id = "4">
<mezo id = "datum">20071101</mezo>
<mezo id = "valtk">0</mezo>
<mezo id = "valtv">0</mezo>
<mezo id = "bkelt">0</mezo>
<mezo id = "tkelt">0</mezo>
</alrovat>
<alrovat id = "5">
<mezo id = "datum">20080717</mezo>
<mezo id = "valtk">0</mezo>
<mezo id = "valtv">0</mezo>
<mezo id = "bkelt">0</mezo>
<mezo id = "tkelt">0</mezo>
</alrovat>
<alrovat id = "6">
<mezo id = "datum">20080901</mezo>
<mezo id = "valtk">20080902</mezo>
<mezo id = "valtv">0</mezo>
<mezo id = "bkelt">0</mezo>
<mezo id = "tkelt">0</mezo>
</alrovat>
<alrovat id = "7">
<mezo id = "datum">20081215</mezo>
<mezo id = "valtk">0</mezo>
<mezo id = "valtv">0</mezo>
<mezo id = "bkelt">0</mezo>
<mezo id = "tkelt">0</mezo>
</alrovat>
<alrovat id = "8">
<mezo id = "datum">20100410</mezo>
</alrovat>
</rovat>
<rovat id = "902">
<alrovat id = "25">
<mezo id = "hattol">20080717</mezo>
<mezo id = "fotev">x</mezo>
<mezo id = "hengk1">0</mezo>
<mezo id = "hengv1">0</mezo>
<mezo id = "hengk2">0</mezo>
<mezo id = "hengv2">0</mezo>
<mezo id = "hengk3">0</mezo>
<mezo id = "hengv3">0</mezo>
<mezo id = "hengk4">0</mezo>
<mezo id = "hengv4">0</mezo>
<mezo id = "korlk">0</mezo>
<mezo id = "korlv">0</mezo>
<mezo id = "valtk">20080717</mezo>
<mezo id = "valtv">0</mezo>
<mezo id = "bkelt">20080902</mezo>
<mezo id = "tkelt">0</mezo>
<mezo id = "tea08">4618</mezo>
</alrovat>
<alrovat id = "26">
<mezo id = "hattol">20080717</mezo>
<mezo id = "hengk1">0</mezo>
<mezo id = "hengv1">0</mezo>
<mezo id = "hengk2">0</mezo>
<mezo id = "hengv2">0</mezo>
<mezo id = "hengk3">0</mezo>
<mezo id = "hengv3">0</mezo>
<mezo id = "hengk4">0</mezo>
<mezo id = "hengv4">0</mezo>
<mezo id = "korlk">0</mezo>
<mezo id = "korlv">0</mezo>
<mezo id = "valtk">20080717</mezo>
<mezo id = "valtv">0</mezo>
<mezo id = "bkelt">20080902</mezo>
<mezo id = "tkelt">0</mezo>
<mezo id = "tea08">2680</mezo>
</alrovat>
<alrovat id = "27">
<mezo id = "hattol">20080717</mezo>
<mezo id = "hengk1">0</mezo>
<mezo id = "hengv1">0</mezo>
<mezo id = "hengk2">0</mezo>
<mezo id = "hengv2">0</mezo>
<mezo id = "hengk3">0</mezo>
<mezo id = "hengv3">0</mezo>
<mezo id = "hengk4">0</mezo>
<mezo id = "hengv4">0</mezo>
<mezo id = "korlk">0</mezo>
<mezo id = "korlv">0</mezo>
<mezo id = "valtk">20080717</mezo>
<mezo id = "valtv">0</mezo>
<mezo id = "bkelt">20080902</mezo>
<mezo id = "tkelt">0</mezo>
<mezo id = "tea08">4511</mezo>
</alrovat>
<alrovat id = "28">
<mezo id = "hattol">20080717</mezo>
<mezo id = "hengk1">0</mezo>
<mezo id = "hengv1">0</mezo>
<mezo id = "hengk2">0</mezo>
<mezo id = "hengv2">0</mezo>
<mezo id = "hengk3">0</mezo>
<mezo id = "hengv3">0</mezo>
<mezo id = "hengk4">0</mezo>
<mezo id = "hengv4">0</mezo>
<mezo id = "korlk">0</mezo>
<mezo id = "korlv">0</mezo>
<mezo id = "valtk">20080717</mezo>
<mezo id = "valtv">0</mezo>
<mezo id = "bkelt">20080902</mezo>
<mezo id = "tkelt">0</mezo>
<mezo id = "tea08">4519</mezo>
</alrovat>
<alrovat id = "29">
<mezo id = "hattol">20080717</mezo>
<mezo id = "hengk1">0</mezo>
<mezo id = "hengv1">0</mezo>
<mezo id = "hengk2">0</mezo>
<mezo id = "hengv2">0</mezo>
<mezo id = "hengk3">0</mezo>
<mezo id = "hengv3">0</mezo>
<mezo id = "hengk4">0</mezo>
<mezo id = "hengv4">0</mezo>
<mezo id = "korlk">0</mezo>
<mezo id = "korlv">0</mezo>
<mezo id = "valtk">20080717</mezo>
<mezo id = "valtv">0</mezo>
<mezo id = "bkelt">20080902</mezo>
<mezo id = "tkelt">0</mezo>
<mezo id = "tea08">4520</mezo>
</alrovat>
<alrovat id = "30">
<mezo id = "hattol">20080717</mezo>
<mezo id = "hengk1">0</mezo>
<mezo id = "hengv1">0</mezo>
<mezo id = "hengk2">0</mezo>
<mezo id = "hengv2">0</mezo>
<mezo id = "hengk3">0</mezo>
<mezo id = "hengv3">0</mezo>
<mezo id = "hengk4">0</mezo>
<mezo id = "hengv4">0</mezo>
<mezo id = "korlk">0</mezo>
<mezo id = "korlv">0</mezo>
<mezo id = "valtk">20080717</mezo>
<mezo id = "valtv">0</mezo>
<mezo id = "bkelt">20080902</mezo>
<mezo id = "tkelt">0</mezo>
<mezo id = "tea08">4531</mezo>
</alrovat>
<alrovat id = "31">
<mezo id = "hattol">20080717</mezo>
<mezo id = "hengk1">0</mezo>
<mezo id = "hengv1">0</mezo>
<mezo id = "hengk2">0</mezo>
<mezo id = "hengv2">0</mezo>
<mezo id = "hengk3">0</mezo>
<mezo id = "hengv3">0</mezo>
<mezo id = "hengk4">0</mezo>
<mezo id = "hengv4">0</mezo>
<mezo id = "korlk">0</mezo>
<mezo id = "korlv">0</mezo>
<mezo id = "valtk">20080717</mezo>
<mezo id = "valtv">0</mezo>
<mezo id = "bkelt">20080902</mezo>
<mezo id = "tkelt">0</mezo>
<mezo id = "tea08">4532</mezo>
</alrovat>
<alrovat id = "32">
<mezo id = "hattol">20080717</mezo>
<mezo id = "hengk1">0</mezo>
<mezo id = "hengv1">0</mezo>
<mezo id = "hengk2">0</mezo>
<mezo id = "hengv2">0</mezo>
<mezo id = "hengk3">0</mezo>
<mezo id = "hengv3">0</mezo>
<mezo id = "hengk4">0</mezo>
<mezo id = "hengv4">0</mezo>
<mezo id = "korlk">0</mezo>
<mezo id = "korlv">0</mezo>
<mezo id = "valtk">20080717</mezo>
<mezo id = "valtv">0</mezo>
<mezo id = "bkelt">20080902</mezo>
<mezo id = "tkelt">0</mezo>
<mezo id = "tea08">4540</mezo>
</alrovat>
<alrovat id = "33">
<mezo id = "hattol">20080717</mezo>
<mezo id = "hengk1">0</mezo>
<mezo id = "hengv1">0</mezo>
<mezo id = "hengk2">0</mezo>
<mezo id = "hengv2">0</mezo>
<mezo id = "hengk3">0</mezo>
<mezo id = "hengv3">0</mezo>
<mezo id = "hengk4">0</mezo>
<mezo id = "hengv4">0</mezo>
<mezo id = "korlk">0</mezo>
<mezo id = "korlv">0</mezo>
<mezo id = "valtk">20080717</mezo>
<mezo id = "valtv">0</mezo>
<mezo id = "bkelt">20080902</mezo>
<mezo id = "tkelt">0</mezo>
<mezo id = "tea08">4614</mezo>
</alrovat>
<alrovat id = "34">
<mezo id = "hattol">20080717</mezo>
<mezo id = "hengk1">0</mezo>
<mezo id = "hengv1">0</mezo>
<mezo id = "hengk2">0</mezo>
<mezo id = "hengv2">0</mezo>
<mezo id = "hengk3">0</mezo>
<mezo id = "hengv3">0</mezo>
<mezo id = "hengk4">0</mezo>
<mezo id = "hengv4">0</mezo>
<mezo id = "korlk">0</mezo>
<mezo id = "korlv">0</mezo>
<mezo id = "valtk">20080717</mezo>
<mezo id = "valtv">0</mezo>
<mezo id = "bkelt">20080902</mezo>
<mezo id = "tkelt">0</mezo>
<mezo id = "tea08">4618</mezo>
</alrovat>
<alrovat id = "35">
<mezo id = "hattol">20080717</mezo>
<mezo id = "hengk1">0</mezo>
<mezo id = "hengv1">0</mezo>
<mezo id = "hengk2">0</mezo>
<mezo id = "hengv2">0</mezo>
<mezo id = "hengk3">0</mezo>
<mezo id = "hengv3">0</mezo>
<mezo id = "hengk4">0</mezo>
<mezo id = "hengv4">0</mezo>
<mezo id = "korlk">0</mezo>
<mezo id = "korlv">0</mezo>
<mezo id = "valtk">20080717</mezo>
<mezo id = "valtv">0</mezo>
<mezo id = "bkelt">20080902</mezo>
<mezo id = "tkelt">0</mezo>
<mezo id = "tea08">4638</mezo>
</alrovat>
<alrovat id = "36">
<mezo id = "hattol">20080717</mezo>
<mezo id = "hengk1">0</mezo>
<mezo id = "hengv1">0</mezo>
<mezo id = "hengk2">0</mezo>
<mezo id = "hengv2">0</mezo>
<mezo id = "hengk3">0</mezo>
<mezo id = "hengv3">0</mezo>
<mezo id = "hengk4">0</mezo>
<mezo id = "hengv4">0</mezo>
<mezo id = "korlk">0</mezo>
<mezo id = "korlv">0</mezo>
<mezo id = "valtk">20080717</mezo>
<mezo id = "valtv">0</mezo>
<mezo id = "bkelt">20080902</mezo>
<mezo id = "tkelt">0</mezo>
<mezo id = "tea08">4643</mezo>
</alrovat>
<alrovat id = "37">
<mezo id = "hattol">20080717</mezo>
<mezo id = "hengk1">0</mezo>
<mezo id = "hengv1">0</mezo>
<mezo id = "hengk2">0</mezo>
<mezo id = "hengv2">0</mezo>
<mezo id = "hengk3">0</mezo>
<mezo id = "hengv3">0</mezo>
<mezo id = "hengk4">0</mezo>
<mezo id = "hengv4">0</mezo>
<mezo id = "korlk">0</mezo>
<mezo id = "korlv">0</mezo>
<mezo id = "valtk">20080717</mezo>
<mezo id = "valtv">0</mezo>
<mezo id = "bkelt">20080902</mezo>
<mezo id = "tkelt">0</mezo>
<mezo id = "tea08">4647</mezo>
</alrovat>
<alrovat id = "38">
<mezo id = "hattol">20080717</mezo>
<mezo id = "hengk1">0</mezo>
<mezo id = "hengv1">0</mezo>
<mezo id = "hengk2">0</mezo>
<mezo id = "hengv2">0</mezo>
<mezo id = "hengk3">0</mezo>
<mezo id = "hengv3">0</mezo>
<mezo id = "hengk4">0</mezo>
<mezo id = "hengv4">0</mezo>
<mezo id = "korlk">0</mezo>
<mezo id = "korlv">0</mezo>
<mezo id = "valtk">20080717</mezo>
<mezo id = "valtv">0</mezo>
<mezo id = "bkelt">20080902</mezo>
<mezo id = "tkelt">0</mezo>
<mezo id = "tea08">4648</mezo>
</alrovat>
<alrovat id = "39">
<mezo id = "hattol">20080717</mezo>
<mezo id = "hengk1">0</mezo>
<mezo id = "hengv1">0</mezo>
<mezo id = "hengk2">0</mezo>
<mezo id = "hengv2">0</mezo>
<mezo id = "hengk3">0</mezo>
<mezo id = "hengv3">0</mezo>
<mezo id = "hengk4">0</mezo>
<mezo id = "hengv4">0</mezo>
<mezo id = "korlk">0</mezo>
<mezo id = "korlv">0</mezo>
<mezo id = "valtk">20080717</mezo>
<mezo id = "valtv">0</mezo>
<mezo id = "bkelt">20080902</mezo>
<mezo id = "tkelt">0</mezo>
<mezo id = "tea08">4649</mezo>
</alrovat>
<alrovat id = "40">
<mezo id = "hattol">20080717</mezo>
<mezo id = "hengk1">0</mezo>
<mezo id = "hengv1">0</mezo>
<mezo id = "hengk2">0</mezo>
<mezo id = "hengv2">0</mezo>
<mezo id = "hengk3">0</mezo>
<mezo id = "hengv3">0</mezo>
<mezo id = "hengk4">0</mezo>
<mezo id = "hengv4">0</mezo>
<mezo id = "korlk">0</mezo>
<mezo id = "korlv">0</mezo>
<mezo id = "valtk">20080717</mezo>
<mezo id = "valtv">0</mezo>
<mezo id = "bkelt">20080902</mezo>
<mezo id = "tkelt">0</mezo>
<mezo id = "tea08">4651</mezo>
</alrovat>
<alrovat id = "41">
<mezo id = "hattol">20080717</mezo>
<mezo id = "hengk1">0</mezo>
<mezo id = "hengv1">0</mezo>
<mezo id = "hengk2">0</mezo>
<mezo id = "hengv2">0</mezo>
<mezo id = "hengk3">0</mezo>
<mezo id = "hengv3">0</mezo>
<mezo id = "hengk4">0</mezo>
<mezo id = "hengv4">0</mezo>
<mezo id = "korlk">0</mezo>
<mezo id = "korlv">0</mezo>
<mezo id = "valtk">20080717</mezo>
<mezo id = "valtv">0</mezo>
<mezo id = "bkelt">20080902</mezo>
<mezo id = "tkelt">0</mezo>
<mezo id = "tea08">4652</mezo>
</alrovat>
<alrovat id = "42">
<mezo id = "hattol">20080717</mezo>
<mezo id = "hengk1">0</mezo>
<mezo id = "hengv1">0</mezo>
<mezo id = "hengk2">0</mezo>
<mezo id = "hengv2">0</mezo>
<mezo id = "hengk3">0</mezo>
<mezo id = "hengv3">0</mezo>
<mezo id = "hengk4">0</mezo>
<mezo id = "hengv4">0</mezo>
<mezo id = "korlk">0</mezo>
<mezo id = "korlv">0</mezo>
<mezo id = "valtk">20080717</mezo>
<mezo id = "valtv">0</mezo>
<mezo id = "bkelt">20080902</mezo>
<mezo id = "tkelt">0</mezo>
<mezo id = "tea08">4673</mezo>
</alrovat>
<alrovat id = "43">
<mezo id = "hattol">20080717</mezo>
<mezo id = "hengk1">0</mezo>
<mezo id = "hengv1">0</mezo>
<mezo id = "hengk2">0</mezo>
<mezo id = "hengv2">0</mezo>
<mezo id = "hengk3">0</mezo>
<mezo id = "hengv3">0</mezo>
<mezo id = "hengk4">0</mezo>
<mezo id = "hengv4">0</mezo>
<mezo id = "korlk">0</mezo>
<mezo id = "korlv">0</mezo>
<mezo id = "valtk">20080717</mezo>
<mezo id = "valtv">0</mezo>
<mezo id = "bkelt">20080902</mezo>
<mezo id = "tkelt">0</mezo>
<mezo id = "tea08">4741</mezo>
</alrovat>
<alrovat id = "44">
<mezo id = "hattol">20080717</mezo>
<mezo id = "hengk1">0</mezo>
<mezo id = "hengv1">0</mezo>
<mezo id = "hengk2">0</mezo>
<mezo id = "hengv2">0</mezo>
<mezo id = "hengk3">0</mezo>
<mezo id = "hengv3">0</mezo>
<mezo id = "hengk4">0</mezo>
<mezo id = "hengv4">0</mezo>
<mezo id = "korlk">0</mezo>
<mezo id = "korlv">0</mezo>
<mezo id = "valtk">20080717</mezo>
<mezo id = "valtv">0</mezo>
<mezo id = "bkelt">20080902</mezo>
<mezo id = "tkelt">0</mezo>
<mezo id = "tea08">4742</mezo>
</alrovat>
<alrovat id = "45">
<mezo id = "hattol">20080717</mezo>
<mezo id = "hengk1">0</mezo>
<mezo id = "hengv1">0</mezo>
<mezo id = "hengk2">0</mezo>
<mezo id = "hengv2">0</mezo>
<mezo id = "hengk3">0</mezo>
<mezo id = "hengv3">0</mezo>
<mezo id = "hengk4">0</mezo>
<mezo id = "hengv4">0</mezo>
<mezo id = "korlk">0</mezo>
<mezo id = "korlv">0</mezo>
<mezo id = "valtk">20080717</mezo>
<mezo id = "valtv">0</mezo>
<mezo id = "bkelt">20080902</mezo>
<mezo id = "tkelt">0</mezo>
<mezo id = "tea08">4753</mezo>
</alrovat>
<alrovat id = "46">
<mezo id = "hattol">20080717</mezo>
<mezo id = "hengk1">0</mezo>
<mezo id = "hengv1">0</mezo>
<mezo id = "hengk2">0</mezo>
<mezo id = "hengv2">0</mezo>
<mezo id = "hengk3">0</mezo>
<mezo id = "hengv3">0</mezo>
<mezo id = "hengk4">0</mezo>
<mezo id = "hengv4">0</mezo>
<mezo id = "korlk">0</mezo>
<mezo id = "korlv">0</mezo>
<mezo id = "valtk">20080717</mezo>
<mezo id = "valtv">0</mezo>
<mezo id = "bkelt">20080902</mezo>
<mezo id = "tkelt">0</mezo>
<mezo id = "tea08">4759</mezo>
</alrovat>
<alrovat id = "47">
<mezo id = "hattol">20080717</mezo>
<mezo id = "hengk1">0</mezo>
<mezo id = "hengv1">0</mezo>
<mezo id = "hengk2">0</mezo>
<mezo id = "hengv2">0</mezo>
<mezo id = "hengk3">0</mezo>
<mezo id = "hengv3">0</mezo>
<mezo id = "hengk4">0</mezo>
<mezo id = "hengv4">0</mezo>
<mezo id = "korlk">0</mezo>
<mezo id = "korlv">0</mezo>
<mezo id = "valtk">20080717</mezo>
<mezo id = "valtv">0</mezo>
<mezo id = "bkelt">20080902</mezo>
<mezo id = "tkelt">0</mezo>
<mezo id = "tea08">4764</mezo>
</alrovat>
<alrovat id = "48">
<mezo id = "hattol">20080717</mezo>
<mezo id = "hengk1">0</mezo>
<mezo id = "hengv1">0</mezo>
<mezo id = "hengk2">0</mezo>
<mezo id = "hengv2">0</mezo>
<mezo id = "hengk3">0</mezo>
<mezo id = "hengv3">0</mezo>
<mezo id = "hengk4">0</mezo>
<mezo id = "hengv4">0</mezo>
<mezo id = "korlk">0</mezo>
<mezo id = "korlv">0</mezo>
<mezo id = "valtk">20080717</mezo>
<mezo id = "valtv">0</mezo>
<mezo id = "bkelt">20080902</mezo>
<mezo id = "tkelt">0</mezo>
<mezo id = "tea08">4765</mezo>
</alrovat>
<alrovat id = "49">
<mezo id = "hattol">20080717</mezo>
<mezo id = "hengk1">0</mezo>
<mezo id = "hengv1">0</mezo>
<mezo id = "hengk2">0</mezo>
<mezo id = "hengv2">0</mezo>
<mezo id = "hengk3">0</mezo>
<mezo id = "hengv3">0</mezo>
<mezo id = "hengk4">0</mezo>
<mezo id = "hengv4">0</mezo>
<mezo id = "korlk">0</mezo>
<mezo id = "korlv">0</mezo>
<mezo id = "valtk">20080717</mezo>
<mezo id = "valtv">0</mezo>
<mezo id = "bkelt">20080902</mezo>
<mezo id = "tkelt">0</mezo>
<mezo id = "tea08">4776</mezo>
</alrovat>
<alrovat id = "50">
<mezo id = "hattol">20080717</mezo>
<mezo id = "hengk1">0</mezo>
<mezo id = "hengv1">0</mezo>
<mezo id = "hengk2">0</mezo>
<mezo id = "hengv2">0</mezo>
<mezo id = "hengk3">0</mezo>
<mezo id = "hengv3">0</mezo>
<mezo id = "hengk4">0</mezo>
<mezo id = "hengv4">0</mezo>
<mezo id = "korlk">0</mezo>
<mezo id = "korlv">0</mezo>
<mezo id = "valtk">20080717</mezo>
<mezo id = "valtv">0</mezo>
<mezo id = "bkelt">20080902</mezo>
<mezo id = "tkelt">0</mezo>
<mezo id = "tea08">4777</mezo>
</alrovat>
<alrovat id = "51">
<mezo id = "hattol">20080717</mezo>
<mezo id = "hengk1">0</mezo>
<mezo id = "hengv1">0</mezo>
<mezo id = "hengk2">0</mezo>
<mezo id = "hengv2">0</mezo>
<mezo id = "hengk3">0</mezo>
<mezo id = "hengv3">0</mezo>
<mezo id = "hengk4">0</mezo>
<mezo id = "hengv4">0</mezo>
<mezo id = "korlk">0</mezo>
<mezo id = "korlv">0</mezo>
<mezo id = "valtk">20080717</mezo>
<mezo id = "valtv">0</mezo>
<mezo id = "bkelt">20080902</mezo>
<mezo id = "tkelt">0</mezo>
<mezo id = "tea08">4778</mezo>
</alrovat>
<alrovat id = "52">
<mezo id = "hattol">20080717</mezo>
<mezo id = "hengk1">0</mezo>
<mezo id = "hengv1">0</mezo>
<mezo id = "hengk2">0</mezo>
<mezo id = "hengv2">0</mezo>
<mezo id = "hengk3">0</mezo>
<mezo id = "hengv3">0</mezo>
<mezo id = "hengk4">0</mezo>
<mezo id = "hengv4">0</mezo>
<mezo id = "korlk">0</mezo>
<mezo id = "korlv">0</mezo>
<mezo id = "valtk">20080717</mezo>
<mezo id = "valtv">0</mezo>
<mezo id = "bkelt">20080902</mezo>
<mezo id = "tkelt">0</mezo>
<mezo id = "tea08">5221</mezo>
</alrovat>
<alrovat id = "53">
<mezo id = "hattol">20080717</mezo>
<mezo id = "hengk1">0</mezo>
<mezo id = "hengv1">0</mezo>
<mezo id = "hengk2">0</mezo>
<mezo id = "hengv2">0</mezo>
<mezo id = "hengk3">0</mezo>
<mezo id = "hengv3">0</mezo>
<mezo id = "hengk4">0</mezo>
<mezo id = "hengv4">0</mezo>
<mezo id = "korlk">0</mezo>
<mezo id = "korlv">0</mezo>
<mezo id = "valtk">20080717</mezo>
<mezo id = "valtv">0</mezo>
<mezo id = "bkelt">20080902</mezo>
<mezo id = "tkelt">0</mezo>
<mezo id = "tea08">5811</mezo>
</alrovat>
<alrovat id = "54">
<mezo id = "hattol">20080717</mezo>
<mezo id = "hengk1">0</mezo>
<mezo id = "hengv1">0</mezo>
<mezo id = "hengk2">0</mezo>
<mezo id = "hengv2">0</mezo>
<mezo id = "hengk3">0</mezo>
<mezo id = "hengv3">0</mezo>
<mezo id = "hengk4">0</mezo>
<mezo id = "hengv4">0</mezo>
<mezo id = "korlk">0</mezo>
<mezo id = "korlv">0</mezo>
<mezo id = "valtk">20080717</mezo>
<mezo id = "valtv">0</mezo>
<mezo id = "bkelt">20080902</mezo>
<mezo id = "tkelt">0</mezo>
<mezo id = "tea08">5812</mezo>
</alrovat>
<alrovat id = "55">
<mezo id = "hattol">20080717</mezo>
<mezo id = "hengk1">0</mezo>
<mezo id = "hengv1">0</mezo>
<mezo id = "hengk2">0</mezo>
<mezo id = "hengv2">0</mezo>
<mezo id = "hengk3">0</mezo>
<mezo id = "hengv3">0</mezo>
<mezo id = "hengk4">0</mezo>
<mezo id = "hengv4">0</mezo>
<mezo id = "korlk">0</mezo>
<mezo id = "korlv">0</mezo>
<mezo id = "valtk">20080717</mezo>
<mezo id = "valtv">0</mezo>
<mezo id = "bkelt">20080902</mezo>
<mezo id = "tkelt">0</mezo>
<mezo id = "tea08">5813</mezo>
</alrovat>
<alrovat id = "56">
<mezo id = "hattol">20080717</mezo>
<mezo id = "hengk1">0</mezo>
<mezo id = "hengv1">0</mezo>
<mezo id = "hengk2">0</mezo>
<mezo id = "hengv2">0</mezo>
<mezo id = "hengk3">0</mezo>
<mezo id = "hengv3">0</mezo>
<mezo id = "hengk4">0</mezo>
<mezo id = "hengv4">0</mezo>
<mezo id = "korlk">0</mezo>
<mezo id = "korlv">0</mezo>
<mezo id = "valtk">20080717</mezo>
<mezo id = "valtv">0</mezo>
<mezo id = "bkelt">20080902</mezo>
<mezo id = "tkelt">0</mezo>
<mezo id = "tea08">5814</mezo>
</alrovat>
<alrovat id = "57">
<mezo id = "hattol">20080717</mezo>
<mezo id = "hengk1">0</mezo>
<mezo id = "hengv1">0</mezo>
<mezo id = "hengk2">0</mezo>
<mezo id = "hengv2">0</mezo>
<mezo id = "hengk3">0</mezo>
<mezo id = "hengv3">0</mezo>
<mezo id = "hengk4">0</mezo>
<mezo id = "hengv4">0</mezo>
<mezo id = "korlk">0</mezo>
<mezo id = "korlv">0</mezo>
<mezo id = "valtk">20080717</mezo>
<mezo id = "valtv">0</mezo>
<mezo id = "bkelt">20080902</mezo>
<mezo id = "tkelt">0</mezo>
<mezo id = "tea08">5821</mezo>
</alrovat>
<alrovat id = "58">
<mezo id = "hattol">20080717</mezo>
<mezo id = "hengk1">0</mezo>
<mezo id = "hengv1">0</mezo>
<mezo id = "hengk2">0</mezo>
<mezo id = "hengv2">0</mezo>
<mezo id = "hengk3">0</mezo>
<mezo id = "hengv3">0</mezo>
<mezo id = "hengk4">0</mezo>
<mezo id = "hengv4">0</mezo>
<mezo id = "korlk">0</mezo>
<mezo id = "korlv">0</mezo>
<mezo id = "valtk">20080717</mezo>
<mezo id = "valtv">0</mezo>
<mezo id = "bkelt">20080902</mezo>
<mezo id = "tkelt">0</mezo>
<mezo id = "tea08">5829</mezo>
</alrovat>
<alrovat id = "59">
<mezo id = "hattol">20080717</mezo>
<mezo id = "hengk1">0</mezo>
<mezo id = "hengv1">0</mezo>
<mezo id = "hengk2">0</mezo>
<mezo id = "hengv2">0</mezo>
<mezo id = "hengk3">0</mezo>
<mezo id = "hengv3">0</mezo>
<mezo id = "hengk4">0</mezo>
<mezo id = "hengv4">0</mezo>
<mezo id = "korlk">0</mezo>
<mezo id = "korlv">0</mezo>
<mezo id = "valtk">20080717</mezo>
<mezo id = "valtv">0</mezo>
<mezo id = "bkelt">20080902</mezo>
<mezo id = "tkelt">0</mezo>
<mezo id = "tea08">5920</mezo>
</alrovat>
<alrovat id = "60">
<mezo id = "hattol">20080717</mezo>
<mezo id = "hengk1">0</mezo>
<mezo id = "hengv1">0</mezo>
<mezo id = "hengk2">0</mezo>
<mezo id = "hengv2">0</mezo>
<mezo id = "hengk3">0</mezo>
<mezo id = "hengv3">0</mezo>
<mezo id = "hengk4">0</mezo>
<mezo id = "hengv4">0</mezo>
<mezo id = "korlk">0</mezo>
<mezo id = "korlv">0</mezo>
<mezo id = "valtk">20080717</mezo>
<mezo id = "valtv">0</mezo>
<mezo id = "bkelt">20080902</mezo>
<mezo id = "tkelt">0</mezo>
<mezo id = "tea08">6110</mezo>
</alrovat>
<alrovat id = "61">
<mezo id = "hattol">20080717</mezo>
<mezo id = "hengk1">0</mezo>
<mezo id = "hengv1">0</mezo>
<mezo id = "hengk2">0</mezo>
<mezo id = "hengv2">0</mezo>
<mezo id = "hengk3">0</mezo>
<mezo id = "hengv3">0</mezo>
<mezo id = "hengk4">0</mezo>
<mezo id = "hengv4">0</mezo>
<mezo id = "korlk">0</mezo>
<mezo id = "korlv">0</mezo>
<mezo id = "valtk">20080717</mezo>
<mezo id = "valtv">0</mezo>
<mezo id = "bkelt">20080902</mezo>
<mezo id = "tkelt">0</mezo>
<mezo id = "tea08">6120</mezo>
</alrovat>
<alrovat id = "62">
<mezo id = "hattol">20080717</mezo>
<mezo id = "hengk1">0</mezo>
<mezo id = "hengv1">0</mezo>
<mezo id = "hengk2">0</mezo>
<mezo id = "hengv2">0</mezo>
<mezo id = "hengk3">0</mezo>
<mezo id = "hengv3">0</mezo>
<mezo id = "hengk4">0</mezo>
<mezo id = "hengv4">0</mezo>
<mezo id = "korlk">0</mezo>
<mezo id = "korlv">0</mezo>
<mezo id = "valtk">20080717</mezo>
<mezo id = "valtv">0</mezo>
<mezo id = "bkelt">20080902</mezo>
<mezo id = "tkelt">0</mezo>
<mezo id = "tea08">6190</mezo>
</alrovat>
<alrovat id = "63">
<mezo id = "hattol">20080717</mezo>
<mezo id = "hengk1">0</mezo>
<mezo id = "hengv1">0</mezo>
<mezo id = "hengk2">0</mezo>
<mezo id = "hengv2">0</mezo>
<mezo id = "hengk3">0</mezo>
<mezo id = "hengv3">0</mezo>
<mezo id = "hengk4">0</mezo>
<mezo id = "hengv4">0</mezo>
<mezo id = "korlk">0</mezo>
<mezo id = "korlv">0</mezo>
<mezo id = "valtk">20080717</mezo>
<mezo id = "valtv">0</mezo>
<mezo id = "bkelt">20080902</mezo>
<mezo id = "tkelt">0</mezo>
<mezo id = "tea08">6201</mezo>
</alrovat>
<alrovat id = "64">
<mezo id = "hattol">20080717</mezo>
<mezo id = "hengk1">0</mezo>
<mezo id = "hengv1">0</mezo>
<mezo id = "hengk2">0</mezo>
<mezo id = "hengv2">0</mezo>
<mezo id = "hengk3">0</mezo>
<mezo id = "hengv3">0</mezo>
<mezo id = "hengk4">0</mezo>
<mezo id = "hengv4">0</mezo>
<mezo id = "korlk">0</mezo>
<mezo id = "korlv">0</mezo>
<mezo id = "valtk">20080717</mezo>
<mezo id = "valtv">0</mezo>
<mezo id = "bkelt">20080902</mezo>
<mezo id = "tkelt">0</mezo>
<mezo id = "tea08">6202</mezo>
</alrovat>
<alrovat id = "65">
<mezo id = "hattol">20080717</mezo>
<mezo id = "hengk1">0</mezo>
<mezo id = "hengv1">0</mezo>
<mezo id = "hengk2">0</mezo>
<mezo id = "hengv2">0</mezo>
<mezo id = "hengk3">0</mezo>
<mezo id = "hengv3">0</mezo>
<mezo id = "hengk4">0</mezo>
<mezo id = "hengv4">0</mezo>
<mezo id = "korlk">0</mezo>
<mezo id = "korlv">0</mezo>
<mezo id = "valtk">20080717</mezo>
<mezo id = "valtv">0</mezo>
<mezo id = "bkelt">20080902</mezo>
<mezo id = "tkelt">0</mezo>
<mezo id = "tea08">6203</mezo>
</alrovat>
<alrovat id = "66">
<mezo id = "hattol">20080717</mezo>
<mezo id = "hengk1">0</mezo>
<mezo id = "hengv1">0</mezo>
<mezo id = "hengk2">0</mezo>
<mezo id = "hengv2">0</mezo>
<mezo id = "hengk3">0</mezo>
<mezo id = "hengv3">0</mezo>
<mezo id = "hengk4">0</mezo>
<mezo id = "hengv4">0</mezo>
<mezo id = "korlk">0</mezo>
<mezo id = "korlv">0</mezo>
<mezo id = "valtk">20080717</mezo>
<mezo id = "valtv">0</mezo>
<mezo id = "bkelt">20080902</mezo>
<mezo id = "tkelt">0</mezo>
<mezo id = "tea08">6209</mezo>
</alrovat>
<alrovat id = "67">
<mezo id = "hattol">20080717</mezo>
<mezo id = "hengk1">0</mezo>
<mezo id = "hengv1">0</mezo>
<mezo id = "hengk2">0</mezo>
<mezo id = "hengv2">0</mezo>
<mezo id = "hengk3">0</mezo>
<mezo id = "hengv3">0</mezo>
<mezo id = "hengk4">0</mezo>
<mezo id = "hengv4">0</mezo>
<mezo id = "korlk">0</mezo>
<mezo id = "korlv">0</mezo>
<mezo id = "valtk">20080717</mezo>
<mezo id = "valtv">0</mezo>
<mezo id = "bkelt">20080902</mezo>
<mezo id = "tkelt">0</mezo>
<mezo id = "tea08">6311</mezo>
</alrovat>
<alrovat id = "68">
<mezo id = "hattol">20080717</mezo>
<mezo id = "hengk1">0</mezo>
<mezo id = "hengv1">0</mezo>
<mezo id = "hengk2">0</mezo>
<mezo id = "hengv2">0</mezo>
<mezo id = "hengk3">0</mezo>
<mezo id = "hengv3">0</mezo>
<mezo id = "hengk4">0</mezo>
<mezo id = "hengv4">0</mezo>
<mezo id = "korlk">0</mezo>
<mezo id = "korlv">0</mezo>
<mezo id = "valtk">20080717</mezo>
<mezo id = "valtv">0</mezo>
<mezo id = "bkelt">20080902</mezo>
<mezo id = "tkelt">0</mezo>
<mezo id = "tea08">7311</mezo>
</alrovat>
<alrovat id = "69">
<mezo id = "hattol">20080717</mezo>
<mezo id = "hengk1">0</mezo>
<mezo id = "hengv1">0</mezo>
<mezo id = "hengk2">0</mezo>
<mezo id = "hengv2">0</mezo>
<mezo id = "hengk3">0</mezo>
<mezo id = "hengv3">0</mezo>
<mezo id = "hengk4">0</mezo>
<mezo id = "hengv4">0</mezo>
<mezo id = "korlk">0</mezo>
<mezo id = "korlv">0</mezo>
<mezo id = "valtk">20080717</mezo>
<mezo id = "valtv">0</mezo>
<mezo id = "bkelt">20080902</mezo>
<mezo id = "tkelt">0</mezo>
<mezo id = "tea08">7312</mezo>
</alrovat>
<alrovat id = "70">
<mezo id = "hattol">20080717</mezo>
<mezo id = "hengk1">0</mezo>
<mezo id = "hengv1">0</mezo>
<mezo id = "hengk2">0</mezo>
<mezo id = "hengv2">0</mezo>
<mezo id = "hengk3">0</mezo>
<mezo id = "hengv3">0</mezo>
<mezo id = "hengk4">0</mezo>
<mezo id = "hengv4">0</mezo>
<mezo id = "korlk">0</mezo>
<mezo id = "korlv">0</mezo>
<mezo id = "valtk">20080717</mezo>
<mezo id = "valtv">0</mezo>
<mezo id = "bkelt">20080902</mezo>
<mezo id = "tkelt">0</mezo>
<mezo id = "tea08">7320</mezo>
</alrovat>
<alrovat id = "71">
<mezo id = "hattol">20080717</mezo>
<mezo id = "hengk1">0</mezo>
<mezo id = "hengv1">0</mezo>
<mezo id = "hengk2">0</mezo>
<mezo id = "hengv2">0</mezo>
<mezo id = "hengk3">0</mezo>
<mezo id = "hengv3">0</mezo>
<mezo id = "hengk4">0</mezo>
<mezo id = "hengv4">0</mezo>
<mezo id = "korlk">0</mezo>
<mezo id = "korlv">0</mezo>
<mezo id = "valtk">20080717</mezo>
<mezo id = "valtv">0</mezo>
<mezo id = "bkelt">20080902</mezo>
<mezo id = "tkelt">0</mezo>
<mezo id = "tea08">7490</mezo>
</alrovat>
<alrovat id = "72">
<mezo id = "hattol">20080717</mezo>
<mezo id = "hengk1">0</mezo>
<mezo id = "hengv1">0</mezo>
<mezo id = "hengk2">0</mezo>
<mezo id = "hengv2">0</mezo>
<mezo id = "hengk3">0</mezo>
<mezo id = "hengv3">0</mezo>
<mezo id = "hengk4">0</mezo>
<mezo id = "hengv4">0</mezo>
<mezo id = "korlk">0</mezo>
<mezo id = "korlv">0</mezo>
<mezo id = "valtk">20080717</mezo>
<mezo id = "valtv">0</mezo>
<mezo id = "bkelt">20080902</mezo>
<mezo id = "tkelt">0</mezo>
<mezo id = "tea08">7739</mezo>
</alrovat>
<alrovat id = "73">
<mezo id = "hattol">20080717</mezo>
<mezo id = "hengk1">0</mezo>
<mezo id = "hengv1">0</mezo>
<mezo id = "hengk2">0</mezo>
<mezo id = "hengv2">0</mezo>
<mezo id = "hengk3">0</mezo>
<mezo id = "hengv3">0</mezo>
<mezo id = "hengk4">0</mezo>
<mezo id = "hengv4">0</mezo>
<mezo id = "korlk">0</mezo>
<mezo id = "korlv">0</mezo>
<mezo id = "valtk">20080717</mezo>
<mezo id = "valtv">0</mezo>
<mezo id = "bkelt">20080902</mezo>
<mezo id = "tkelt">0</mezo>
<mezo id = "tea08">8010</mezo>
</alrovat>
<alrovat id = "74">
<mezo id = "hattol">20080717</mezo>
<mezo id = "hengk1">0</mezo>
<mezo id = "hengv1">0</mezo>
<mezo id = "hengk2">0</mezo>
<mezo id = "hengv2">0</mezo>
<mezo id = "hengk3">0</mezo>
<mezo id = "hengv3">0</mezo>
<mezo id = "hengk4">0</mezo>
<mezo id = "hengv4">0</mezo>
<mezo id = "korlk">0</mezo>
<mezo id = "korlv">0</mezo>
<mezo id = "valtk">20080717</mezo>
<mezo id = "valtv">0</mezo>
<mezo id = "bkelt">20080902</mezo>
<mezo id = "tkelt">0</mezo>
<mezo id = "tea08">8020</mezo>
</alrovat>
<alrovat id = "75">
<mezo id = "hattol">20080717</mezo>
<mezo id = "hengk1">0</mezo>
<mezo id = "hengv1">0</mezo>
<mezo id = "hengk2">0</mezo>
<mezo id = "hengv2">0</mezo>
<mezo id = "hengk3">0</mezo>
<mezo id = "hengv3">0</mezo>
<mezo id = "hengk4">0</mezo>
<mezo id = "hengv4">0</mezo>
<mezo id = "korlk">0</mezo>
<mezo id = "korlv">0</mezo>
<mezo id = "valtk">20080717</mezo>
<mezo id = "valtv">0</mezo>
<mezo id = "bkelt">20080902</mezo>
<mezo id = "tkelt">0</mezo>
<mezo id = "tea08">8030</mezo>
</alrovat>
<alrovat id = "76">
<mezo id = "hattol">20080717</mezo>
<mezo id = "hengk1">0</mezo>
<mezo id = "hengv1">0</mezo>
<mezo id = "hengk2">0</mezo>
<mezo id = "hengv2">0</mezo>
<mezo id = "hengk3">0</mezo>
<mezo id = "hengv3">0</mezo>
<mezo id = "hengk4">0</mezo>
<mezo id = "hengv4">0</mezo>
<mezo id = "korlk">0</mezo>
<mezo id = "korlv">0</mezo>
<mezo id = "valtk">20080717</mezo>
<mezo id = "valtv">0</mezo>
<mezo id = "bkelt">20080902</mezo>
<mezo id = "tkelt">0</mezo>
<mezo id = "tea08">8220</mezo>
</alrovat>
<alrovat id = "77">
<mezo id = "hattol">20080717</mezo>
<mezo id = "hengk1">0</mezo>
<mezo id = "hengv1">0</mezo>
<mezo id = "hengk2">0</mezo>
<mezo id = "hengv2">0</mezo>
<mezo id = "hengk3">0</mezo>
<mezo id = "hengv3">0</mezo>
<mezo id = "hengk4">0</mezo>
<mezo id = "hengv4">0</mezo>
<mezo id = "korlk">0</mezo>
<mezo id = "korlv">0</mezo>
<mezo id = "valtk">20080717</mezo>
<mezo id = "valtv">0</mezo>
<mezo id = "bkelt">20080902</mezo>
<mezo id = "tkelt">0</mezo>
<mezo id = "tea08">8299</mezo>
</alrovat>
<alrovat id = "78">
<mezo id = "hattol">20080717</mezo>
<mezo id = "hengk1">0</mezo>
<mezo id = "hengv1">0</mezo>
<mezo id = "hengk2">0</mezo>
<mezo id = "hengv2">0</mezo>
<mezo id = "hengk3">0</mezo>
<mezo id = "hengv3">0</mezo>
<mezo id = "hengk4">0</mezo>
<mezo id = "hengv4">0</mezo>
<mezo id = "korlk">0</mezo>
<mezo id = "korlv">0</mezo>
<mezo id = "valtk">20080717</mezo>
<mezo id = "valtv">0</mezo>
<mezo id = "bkelt">20080902</mezo>
<mezo id = "tkelt">0</mezo>
<mezo id = "tea08">1820</mezo>
</alrovat>
</rovat>
<rovat id = "11">
<alrovat id = "1">
<mezo id = "hattol">20010205</mezo>
<mezo id = "kp">0</mezo>
<mezo id = "app">0</mezo>
<mezo id = "szam">3000000</mezo>
<mezo id = "penz">Ft</mezo>
</alrovat>
</rovat>
<rovat id = "13">
<alrovat id = "5">
<mezo id = "hattol">20100410</mezo>
<mezo id = "tiszt">vezető tisztségviselő (ügyvezető)</mezo>
<mezo id = "pnev">Tiszai Mihály Tibor</mezo>
<mezo id = "panev">Kovács Julianna</mezo>
<mezo id = "kepvo">x</mezo>
<mezo id = "jogvk">20060424</mezo>
<mezo id = "jogvv">20110423</mezo>
<mezo id = "valtk">20100410</mezo>
<mezo id = "bkelt">20100504</mezo>
<mezo id = "adoazon">8384503540</mezo>
</alrovat>
</rovat>
<rovat id = "20">
<alrovat id = "2">
<mezo id = "hattol">20060516</mezo>
<mezo id = "kshsz">12592751511811315</mezo>
</alrovat>
</rovat>
<rovat id = "21">
<alrovat id = "2">
<mezo id = "hattol">20080818</mezo>
<mezo id = "adosz">12592751215</mezo>
<mezo id = "kadosz">HU12592751</mezo>
<mezo id = "nydat">20080604</mezo>
<mezo id = "fkdat">0</mezo>
<mezo id = "fmdat">0</mezo>
<mezo id = "jtdat">0</mezo>
<mezo id = "hmdat">0</mezo>
<mezo id = "hkdat">0</mezo>
<mezo id = "valtk">0</mezo>
<mezo id = "valtv">0</mezo>
<mezo id = "bkelt">20080818</mezo>
<mezo id = "tkelt">0</mezo>
</alrovat>
</rovat>
<rovat id = "0109">
<alrovat id = "6">
<mezo id = "hattol">20071101</mezo>
<mezo id = "pnev">Tiszai Mihály Tibor</mezo>
<mezo id = "panev">Kovács Julianna</mezo>
<mezo id = "pirsz">4481</mezo>
<mezo id = "phely">Nyíregyháza, Jázmin u. 52.</mezo>
<mezo id = "tagsk">20060424</mezo>
<mezo id = "tagsv">0</mezo>
<mezo id = "sz2">x</mezo>
<mezo id = "valtk">20071101</mezo>
<mezo id = "valtv">0</mezo>
<mezo id = "bkelt">20071213</mezo>
<mezo id = "tkelt">0</mezo>
</alrovat>
<alrovat id = "8">
<mezo id = "hattol">20100410</mezo>
<mezo id = "pnev">Hornyák György Zsolt</mezo>
<mezo id = "panev">Smidt Ilona</mezo>
<mezo id = "tagsk">20100410</mezo>
<mezo id = "valtk">20100410</mezo>
<mezo id = "bkelt">20100504</mezo>
</alrovat>
</rovat>
<rovat id = "93">
<alrovat id = "1">
<mezo id = "cegallapot">0</mezo>
</alrovat>
</rovat>
<rovat id = "99">
<alrovat id = "0">
<mezo id = "hattol">0</mezo>
<mezo id = "hatig">0</mezo>
<mezo id = "szoveg">A társaság neve: HUMÁN PORTASZOLGÁLAT Korlátolt Felelősségű Társaság.<ujsor/>
Székhelye: 4481 Nyíregyháza-Sóstóhegy, Kertész u. 14.<ujsor/>
Cégjegyzékszám: Cg. [15 09 066727].<ujsor/>
A befolyást szerző tag neve: Debróczki Tibor.<ujsor/>
Címe: 4481 Nyíregyháza-Sóstóhegy, Kertész u. 14.<ujsor/>
A befolyásszerzés időpontja: 2001. január 12.<ujsor/>
A befolyás mértéke: 60%, többségi irányítást biztosító befolyás.<ujsor/>
A befolyást szerző tag neve: Dobos Csaba.<ujsor/>
Címe: 4400 Nyíregyháza, Ószőlő u. 103. II. 10.<ujsor/>
A befolyásszerzés időpontja: 2001. január 12.<ujsor/>
A befolyás mértéke: 40%, jelentős befolyás.<ujsor/>
</mezo>
<mezo id = "cjsz">1509066727</mezo>
<mezo id = "nev">HUMÁN PORTASZOLGÁLAT Korlátolt Felelősségű Társaság</mezo>
</alrovat>
</rovat>
<rovat id = "99017">
<alrovat id = "1">
<mezo id = "kezd">20070101</mezo>
<mezo id = "veg">20071231</mezo>
<mezo id = "szorzo">1000</mezo>
<mezo id = "penz">HUF</mezo>
<mezo id = "a_eredm">238</mezo>
<mezo id = "aktiv_el">0</mezo>
<mezo id = "eszk">890</mezo>
<mezo id = "celtart">0</mezo>
<mezo id = "netto">28651</mezo>
<mezo id = "forgo">6281</mezo>
<mezo id = "kotelez">4502</mezo>
<mezo id = "m_eredm">190</mezo>
<mezo id = "passziv_el">0</mezo>
<mezo id = "toke">2669</mezo>
<mezo id = "u_eredm">238</mezo>
</alrovat>
<alrovat id = "2">
<mezo id = "kezd">20090101</mezo>
<mezo id = "veg">20091231</mezo>
<mezo id = "szorzo">1000</mezo>
<mezo id = "penz">HUF</mezo>
<mezo id = "a_eredm">2321</mezo>
<mezo id = "aktiv_el">1030</mezo>
<mezo id = "eszk">9333</mezo>
<mezo id = "celtart">0</mezo>
<mezo id = "netto">89867</mezo>
<mezo id = "forgo">8568</mezo>
<mezo id = "kotelez">12474</mezo>
<mezo id = "m_eredm">2098</mezo>
<mezo id = "passziv_el">1020</mezo>
<mezo id = "toke">5437</mezo>
<mezo id = "u_eredm">2320</mezo>
</alrovat>
<alrovat id = "3">
<mezo id = "kezd">20100101</mezo>
<mezo id = "veg">20101231</mezo>
<mezo id = "szorzo">1000</mezo>
<mezo id = "penz">HUF</mezo>
<mezo id = "a_eredm">136</mezo>
<mezo id = "aktiv_el">1194</mezo>
<mezo id = "eszk">10178</mezo>
<mezo id = "celtart">0</mezo>
<mezo id = "netto">40734</mezo>
<mezo id = "forgo">4603</mezo>
<mezo id = "kotelez">9729</mezo>
<mezo id = "m_eredm">95</mezo>
<mezo id = "passziv_el">714</mezo>
<mezo id = "toke">5532</mezo>
<mezo id = "u_eredm">135</mezo>
</alrovat>
</rovat>
</ceg>
