<ceg id="0109265923">
<rovat id = "0">
<alrovat id = "1">
<mezo id = "bir">01</mezo>
<mezo id = "cf">09</mezo>
<mezo id = "szam">265923</mezo>
<mezo id = "nevalrovat">1</mezo>
<mezo id = "cim">1089 Budapest, Vajda Péter u. 10/a. </mezo>
<mezo id = "plus">10</mezo>
<mezo id = "adosz">10861617242</mezo>
</alrovat>
</rovat>
<rovat id = "2">
<alrovat id = "1">
<mezo id = "hattol">19930817</mezo>
<mezo id = "nev">Barhács és Társa Szervezési, Oktatási és Szolgáltató Kft.</mezo>
</alrovat>
</rovat>
<rovat id = "3">
<alrovat id = "1">
<mezo id = "hattol">19930817</mezo>
<mezo id = "nev">Barhács és Társa KFT</mezo>
</alrovat>
</rovat>
<rovat id = "5">
<alrovat id = "3">
<mezo id = "hattol">20080425</mezo>
<mezo id = "irsz">1089</mezo>
<mezo id = "hely">Budapest</mezo>
<mezo id = "teru">Vajda Péter u. 10/a.</mezo>
<mezo id = "kirsz">0</mezo>
<mezo id = "valtk">20080425</mezo>
<mezo id = "valtv">0</mezo>
<mezo id = "bkelt">20080505</mezo>
<mezo id = "tkelt">0</mezo>
</alrovat>
</rovat>
<rovat id = "8">
<alrovat id = "1">
<mezo id = "hattol">19930817</mezo>
<mezo id = "datum">19930817</mezo>
</alrovat>
<alrovat id = "2">
<mezo id = "hattol">19940126</mezo>
<mezo id = "datum">19940126</mezo>
</alrovat>
<alrovat id = "3">
<mezo id = "hattol">19980714</mezo>
<mezo id = "datum">19980702</mezo>
</alrovat>
<alrovat id = "4">
<mezo id = "hattol">19981027</mezo>
<mezo id = "datum">19981022</mezo>
</alrovat>
<alrovat id = "5">
<mezo id = "hattol">20000821</mezo>
<mezo id = "datum">20000613</mezo>
</alrovat>
<alrovat id = "6">
<mezo id = "datum">20070531</mezo>
</alrovat>
<alrovat id = "7">
<mezo id = "datum">20080425</mezo>
<mezo id = "valtk">0</mezo>
<mezo id = "valtv">0</mezo>
<mezo id = "bkelt">0</mezo>
<mezo id = "tkelt">0</mezo>
</alrovat>
<alrovat id = "8">
<mezo id = "datum">20090409</mezo>
<mezo id = "valtk">0</mezo>
<mezo id = "valtv">0</mezo>
<mezo id = "bkelt">0</mezo>
<mezo id = "tkelt">0</mezo>
</alrovat>
<alrovat id = "9">
<mezo id = "datum">20100112</mezo>
</alrovat>
</rovat>
<rovat id = "902">
<alrovat id = "25">
<mezo id = "hattol">20080425</mezo>
<mezo id = "fotev">x</mezo>
<mezo id = "hengk1">0</mezo>
<mezo id = "hengv1">0</mezo>
<mezo id = "hengk2">0</mezo>
<mezo id = "hengv2">0</mezo>
<mezo id = "hengk3">0</mezo>
<mezo id = "hengv3">0</mezo>
<mezo id = "hengk4">0</mezo>
<mezo id = "hengv4">0</mezo>
<mezo id = "korlk">0</mezo>
<mezo id = "korlv">0</mezo>
<mezo id = "valtk">20080425</mezo>
<mezo id = "valtv">0</mezo>
<mezo id = "bkelt">20080505</mezo>
<mezo id = "tkelt">0</mezo>
<mezo id = "tea08">8541</mezo>
</alrovat>
<alrovat id = "26">
<mezo id = "hattol">20080425</mezo>
<mezo id = "hengk1">0</mezo>
<mezo id = "hengv1">0</mezo>
<mezo id = "hengk2">0</mezo>
<mezo id = "hengv2">0</mezo>
<mezo id = "hengk3">0</mezo>
<mezo id = "hengv3">0</mezo>
<mezo id = "hengk4">0</mezo>
<mezo id = "hengv4">0</mezo>
<mezo id = "korlk">0</mezo>
<mezo id = "korlv">0</mezo>
<mezo id = "valtk">20080425</mezo>
<mezo id = "valtv">0</mezo>
<mezo id = "bkelt">20080505</mezo>
<mezo id = "tkelt">0</mezo>
<mezo id = "tea08">1419</mezo>
</alrovat>
<alrovat id = "27">
<mezo id = "hattol">20080425</mezo>
<mezo id = "hengk1">0</mezo>
<mezo id = "hengv1">0</mezo>
<mezo id = "hengk2">0</mezo>
<mezo id = "hengv2">0</mezo>
<mezo id = "hengk3">0</mezo>
<mezo id = "hengv3">0</mezo>
<mezo id = "hengk4">0</mezo>
<mezo id = "hengv4">0</mezo>
<mezo id = "korlk">0</mezo>
<mezo id = "korlv">0</mezo>
<mezo id = "valtk">20080425</mezo>
<mezo id = "valtv">0</mezo>
<mezo id = "bkelt">20080505</mezo>
<mezo id = "tkelt">0</mezo>
<mezo id = "tea08">2620</mezo>
</alrovat>
<alrovat id = "28">
<mezo id = "hattol">20080425</mezo>
<mezo id = "hengk1">0</mezo>
<mezo id = "hengv1">0</mezo>
<mezo id = "hengk2">0</mezo>
<mezo id = "hengv2">0</mezo>
<mezo id = "hengk3">0</mezo>
<mezo id = "hengv3">0</mezo>
<mezo id = "hengk4">0</mezo>
<mezo id = "hengv4">0</mezo>
<mezo id = "korlk">0</mezo>
<mezo id = "korlv">0</mezo>
<mezo id = "valtk">20080425</mezo>
<mezo id = "valtv">0</mezo>
<mezo id = "bkelt">20080505</mezo>
<mezo id = "tkelt">0</mezo>
<mezo id = "tea08">3312</mezo>
</alrovat>
<alrovat id = "29">
<mezo id = "hattol">20080425</mezo>
<mezo id = "hengk1">0</mezo>
<mezo id = "hengv1">0</mezo>
<mezo id = "hengk2">0</mezo>
<mezo id = "hengv2">0</mezo>
<mezo id = "hengk3">0</mezo>
<mezo id = "hengv3">0</mezo>
<mezo id = "hengk4">0</mezo>
<mezo id = "hengv4">0</mezo>
<mezo id = "korlk">0</mezo>
<mezo id = "korlv">0</mezo>
<mezo id = "valtk">20080425</mezo>
<mezo id = "valtv">0</mezo>
<mezo id = "bkelt">20080505</mezo>
<mezo id = "tkelt">0</mezo>
<mezo id = "tea08">3320</mezo>
</alrovat>
<alrovat id = "30">
<mezo id = "hattol">20080425</mezo>
<mezo id = "hengk1">0</mezo>
<mezo id = "hengv1">0</mezo>
<mezo id = "hengk2">0</mezo>
<mezo id = "hengv2">0</mezo>
<mezo id = "hengk3">0</mezo>
<mezo id = "hengv3">0</mezo>
<mezo id = "hengk4">0</mezo>
<mezo id = "hengv4">0</mezo>
<mezo id = "korlk">0</mezo>
<mezo id = "korlv">0</mezo>
<mezo id = "valtk">20080425</mezo>
<mezo id = "valtv">0</mezo>
<mezo id = "bkelt">20080505</mezo>
<mezo id = "tkelt">0</mezo>
<mezo id = "tea08">4339</mezo>
</alrovat>
<alrovat id = "31">
<mezo id = "hattol">20080425</mezo>
<mezo id = "hengk1">0</mezo>
<mezo id = "hengv1">0</mezo>
<mezo id = "hengk2">0</mezo>
<mezo id = "hengv2">0</mezo>
<mezo id = "hengk3">0</mezo>
<mezo id = "hengv3">0</mezo>
<mezo id = "hengk4">0</mezo>
<mezo id = "hengv4">0</mezo>
<mezo id = "korlk">0</mezo>
<mezo id = "korlv">0</mezo>
<mezo id = "valtk">20080425</mezo>
<mezo id = "valtv">0</mezo>
<mezo id = "bkelt">20080505</mezo>
<mezo id = "tkelt">0</mezo>
<mezo id = "tea08">5829</mezo>
</alrovat>
<alrovat id = "32">
<mezo id = "hattol">20080425</mezo>
<mezo id = "hengk1">0</mezo>
<mezo id = "hengv1">0</mezo>
<mezo id = "hengk2">0</mezo>
<mezo id = "hengv2">0</mezo>
<mezo id = "hengk3">0</mezo>
<mezo id = "hengv3">0</mezo>
<mezo id = "hengk4">0</mezo>
<mezo id = "hengv4">0</mezo>
<mezo id = "korlk">0</mezo>
<mezo id = "korlv">0</mezo>
<mezo id = "valtk">20080425</mezo>
<mezo id = "valtv">0</mezo>
<mezo id = "bkelt">20080505</mezo>
<mezo id = "tkelt">0</mezo>
<mezo id = "tea08">6201</mezo>
</alrovat>
<alrovat id = "33">
<mezo id = "hattol">20080425</mezo>
<mezo id = "hengk1">0</mezo>
<mezo id = "hengv1">0</mezo>
<mezo id = "hengk2">0</mezo>
<mezo id = "hengv2">0</mezo>
<mezo id = "hengk3">0</mezo>
<mezo id = "hengv3">0</mezo>
<mezo id = "hengk4">0</mezo>
<mezo id = "hengv4">0</mezo>
<mezo id = "korlk">0</mezo>
<mezo id = "korlv">0</mezo>
<mezo id = "valtk">20080425</mezo>
<mezo id = "valtv">0</mezo>
<mezo id = "bkelt">20080505</mezo>
<mezo id = "tkelt">0</mezo>
<mezo id = "tea08">7022</mezo>
</alrovat>
<alrovat id = "34">
<mezo id = "hattol">20080425</mezo>
<mezo id = "hengk1">0</mezo>
<mezo id = "hengv1">0</mezo>
<mezo id = "hengk2">0</mezo>
<mezo id = "hengv2">0</mezo>
<mezo id = "hengk3">0</mezo>
<mezo id = "hengv3">0</mezo>
<mezo id = "hengk4">0</mezo>
<mezo id = "hengv4">0</mezo>
<mezo id = "korlk">0</mezo>
<mezo id = "korlv">0</mezo>
<mezo id = "valtk">20080425</mezo>
<mezo id = "valtv">0</mezo>
<mezo id = "bkelt">20080505</mezo>
<mezo id = "tkelt">0</mezo>
<mezo id = "tea08">8532</mezo>
</alrovat>
<alrovat id = "35">
<mezo id = "hattol">20080425</mezo>
<mezo id = "hengk1">0</mezo>
<mezo id = "hengv1">0</mezo>
<mezo id = "hengk2">0</mezo>
<mezo id = "hengv2">0</mezo>
<mezo id = "hengk3">0</mezo>
<mezo id = "hengv3">0</mezo>
<mezo id = "hengk4">0</mezo>
<mezo id = "hengv4">0</mezo>
<mezo id = "korlk">0</mezo>
<mezo id = "korlv">0</mezo>
<mezo id = "valtk">20080425</mezo>
<mezo id = "valtv">0</mezo>
<mezo id = "bkelt">20080505</mezo>
<mezo id = "tkelt">0</mezo>
<mezo id = "tea08">8551</mezo>
</alrovat>
<alrovat id = "36">
<mezo id = "hattol">20080425</mezo>
<mezo id = "hengk1">0</mezo>
<mezo id = "hengv1">0</mezo>
<mezo id = "hengk2">0</mezo>
<mezo id = "hengv2">0</mezo>
<mezo id = "hengk3">0</mezo>
<mezo id = "hengv3">0</mezo>
<mezo id = "hengk4">0</mezo>
<mezo id = "hengv4">0</mezo>
<mezo id = "korlk">0</mezo>
<mezo id = "korlv">0</mezo>
<mezo id = "valtk">20080425</mezo>
<mezo id = "valtv">0</mezo>
<mezo id = "bkelt">20080505</mezo>
<mezo id = "tkelt">0</mezo>
<mezo id = "tea08">8552</mezo>
</alrovat>
<alrovat id = "37">
<mezo id = "hattol">20080425</mezo>
<mezo id = "hengk1">0</mezo>
<mezo id = "hengv1">0</mezo>
<mezo id = "hengk2">0</mezo>
<mezo id = "hengv2">0</mezo>
<mezo id = "hengk3">0</mezo>
<mezo id = "hengv3">0</mezo>
<mezo id = "hengk4">0</mezo>
<mezo id = "hengv4">0</mezo>
<mezo id = "korlk">0</mezo>
<mezo id = "korlv">0</mezo>
<mezo id = "valtk">20080425</mezo>
<mezo id = "valtv">0</mezo>
<mezo id = "bkelt">20080505</mezo>
<mezo id = "tkelt">0</mezo>
<mezo id = "tea08">8559</mezo>
</alrovat>
<alrovat id = "38">
<mezo id = "hattol">20080425</mezo>
<mezo id = "hengk1">0</mezo>
<mezo id = "hengv1">0</mezo>
<mezo id = "hengk2">0</mezo>
<mezo id = "hengv2">0</mezo>
<mezo id = "hengk3">0</mezo>
<mezo id = "hengv3">0</mezo>
<mezo id = "hengk4">0</mezo>
<mezo id = "hengv4">0</mezo>
<mezo id = "korlk">0</mezo>
<mezo id = "korlv">0</mezo>
<mezo id = "valtk">20080425</mezo>
<mezo id = "valtv">0</mezo>
<mezo id = "bkelt">20080505</mezo>
<mezo id = "tkelt">0</mezo>
<mezo id = "tea08">8560</mezo>
</alrovat>
<alrovat id = "39">
<mezo id = "hattol">20080425</mezo>
<mezo id = "hengk1">0</mezo>
<mezo id = "hengv1">0</mezo>
<mezo id = "hengk2">0</mezo>
<mezo id = "hengv2">0</mezo>
<mezo id = "hengk3">0</mezo>
<mezo id = "hengv3">0</mezo>
<mezo id = "hengk4">0</mezo>
<mezo id = "hengv4">0</mezo>
<mezo id = "korlk">0</mezo>
<mezo id = "korlv">0</mezo>
<mezo id = "valtk">20080425</mezo>
<mezo id = "valtv">0</mezo>
<mezo id = "bkelt">20080505</mezo>
<mezo id = "tkelt">0</mezo>
<mezo id = "tea08">9511</mezo>
</alrovat>
<alrovat id = "40">
<mezo id = "hattol">20080425</mezo>
<mezo id = "hengk1">0</mezo>
<mezo id = "hengv1">0</mezo>
<mezo id = "hengk2">0</mezo>
<mezo id = "hengv2">0</mezo>
<mezo id = "hengk3">0</mezo>
<mezo id = "hengv3">0</mezo>
<mezo id = "hengk4">0</mezo>
<mezo id = "hengv4">0</mezo>
<mezo id = "korlk">0</mezo>
<mezo id = "korlv">0</mezo>
<mezo id = "valtk">20080425</mezo>
<mezo id = "valtv">0</mezo>
<mezo id = "bkelt">20080505</mezo>
<mezo id = "tkelt">0</mezo>
<mezo id = "tea08">1413</mezo>
</alrovat>
<alrovat id = "41">
<mezo id = "hattol">20080425</mezo>
<mezo id = "hengk1">0</mezo>
<mezo id = "hengv1">0</mezo>
<mezo id = "hengk2">0</mezo>
<mezo id = "hengv2">0</mezo>
<mezo id = "hengk3">0</mezo>
<mezo id = "hengv3">0</mezo>
<mezo id = "hengk4">0</mezo>
<mezo id = "hengv4">0</mezo>
<mezo id = "korlk">0</mezo>
<mezo id = "korlv">0</mezo>
<mezo id = "valtk">20080425</mezo>
<mezo id = "valtv">0</mezo>
<mezo id = "bkelt">20080505</mezo>
<mezo id = "tkelt">0</mezo>
<mezo id = "tea08">1414</mezo>
</alrovat>
<alrovat id = "42">
<mezo id = "hattol">20080425</mezo>
<mezo id = "hengk1">0</mezo>
<mezo id = "hengv1">0</mezo>
<mezo id = "hengk2">0</mezo>
<mezo id = "hengv2">0</mezo>
<mezo id = "hengk3">0</mezo>
<mezo id = "hengv3">0</mezo>
<mezo id = "hengk4">0</mezo>
<mezo id = "hengv4">0</mezo>
<mezo id = "korlk">0</mezo>
<mezo id = "korlv">0</mezo>
<mezo id = "valtk">20080425</mezo>
<mezo id = "valtv">0</mezo>
<mezo id = "bkelt">20080505</mezo>
<mezo id = "tkelt">0</mezo>
<mezo id = "tea08">4331</mezo>
</alrovat>
<alrovat id = "43">
<mezo id = "hattol">20080425</mezo>
<mezo id = "hengk1">0</mezo>
<mezo id = "hengv1">0</mezo>
<mezo id = "hengk2">0</mezo>
<mezo id = "hengv2">0</mezo>
<mezo id = "hengk3">0</mezo>
<mezo id = "hengv3">0</mezo>
<mezo id = "hengk4">0</mezo>
<mezo id = "hengv4">0</mezo>
<mezo id = "korlk">0</mezo>
<mezo id = "korlv">0</mezo>
<mezo id = "valtk">20080425</mezo>
<mezo id = "valtv">0</mezo>
<mezo id = "bkelt">20080505</mezo>
<mezo id = "tkelt">0</mezo>
<mezo id = "tea08">4332</mezo>
</alrovat>
<alrovat id = "44">
<mezo id = "hattol">20080425</mezo>
<mezo id = "hengk1">0</mezo>
<mezo id = "hengv1">0</mezo>
<mezo id = "hengk2">0</mezo>
<mezo id = "hengv2">0</mezo>
<mezo id = "hengk3">0</mezo>
<mezo id = "hengv3">0</mezo>
<mezo id = "hengk4">0</mezo>
<mezo id = "hengv4">0</mezo>
<mezo id = "korlk">0</mezo>
<mezo id = "korlv">0</mezo>
<mezo id = "valtk">20080425</mezo>
<mezo id = "valtv">0</mezo>
<mezo id = "bkelt">20080505</mezo>
<mezo id = "tkelt">0</mezo>
<mezo id = "tea08">4333</mezo>
</alrovat>
<alrovat id = "45">
<mezo id = "hattol">20080425</mezo>
<mezo id = "hengk1">0</mezo>
<mezo id = "hengv1">0</mezo>
<mezo id = "hengk2">0</mezo>
<mezo id = "hengv2">0</mezo>
<mezo id = "hengk3">0</mezo>
<mezo id = "hengv3">0</mezo>
<mezo id = "hengk4">0</mezo>
<mezo id = "hengv4">0</mezo>
<mezo id = "korlk">0</mezo>
<mezo id = "korlv">0</mezo>
<mezo id = "valtk">20080425</mezo>
<mezo id = "valtv">0</mezo>
<mezo id = "bkelt">20080505</mezo>
<mezo id = "tkelt">0</mezo>
<mezo id = "tea08">4334</mezo>
</alrovat>
<alrovat id = "46">
<mezo id = "hattol">20080425</mezo>
<mezo id = "hengk1">0</mezo>
<mezo id = "hengv1">0</mezo>
<mezo id = "hengk2">0</mezo>
<mezo id = "hengv2">0</mezo>
<mezo id = "hengk3">0</mezo>
<mezo id = "hengv3">0</mezo>
<mezo id = "hengk4">0</mezo>
<mezo id = "hengv4">0</mezo>
<mezo id = "korlk">0</mezo>
<mezo id = "korlv">0</mezo>
<mezo id = "valtk">20080425</mezo>
<mezo id = "valtv">0</mezo>
<mezo id = "bkelt">20080505</mezo>
<mezo id = "tkelt">0</mezo>
<mezo id = "tea08">6202</mezo>
</alrovat>
<alrovat id = "47">
<mezo id = "hattol">20080425</mezo>
<mezo id = "hengk1">0</mezo>
<mezo id = "hengv1">0</mezo>
<mezo id = "hengk2">0</mezo>
<mezo id = "hengv2">0</mezo>
<mezo id = "hengk3">0</mezo>
<mezo id = "hengv3">0</mezo>
<mezo id = "hengk4">0</mezo>
<mezo id = "hengv4">0</mezo>
<mezo id = "korlk">0</mezo>
<mezo id = "korlv">0</mezo>
<mezo id = "valtk">20080425</mezo>
<mezo id = "valtv">0</mezo>
<mezo id = "bkelt">20080505</mezo>
<mezo id = "tkelt">0</mezo>
<mezo id = "tea08">6209</mezo>
</alrovat>
</rovat>
<rovat id = "11">
<alrovat id = "2">
<mezo id = "hattol">20000821</mezo>
<mezo id = "kp">3000000</mezo>
<mezo id = "app">0</mezo>
<mezo id = "szam">3000000</mezo>
<mezo id = "penz">Ft</mezo>
</alrovat>
</rovat>
<rovat id = "13">
<alrovat id = "3">
<mezo id = "hattol">20100112</mezo>
<mezo id = "tiszt">vezetõ tisztségviselõ (ügyvezetõ)</mezo>
<mezo id = "pnev">Barhács Anna</mezo>
<mezo id = "panev">Zakar Anna</mezo>
<mezo id = "kepvo">x</mezo>
<mezo id = "jogvk">20070531</mezo>
<mezo id = "valtk">20100112</mezo>
<mezo id = "bkelt">20100126</mezo>
</alrovat>
<alrovat id = "4">
<mezo id = "hattol">20100112</mezo>
<mezo id = "tiszt">vezetõ tisztségviselõ (ügyvezetõ)</mezo>
<mezo id = "pnev">Balogh Gábor</mezo>
<mezo id = "panev">Bankó Ágnes</mezo>
<mezo id = "kepvo">x</mezo>
<mezo id = "jogvk">20100112</mezo>
<mezo id = "jogvv">20111231</mezo>
<mezo id = "valtk">20100112</mezo>
<mezo id = "bkelt">20100126</mezo>
</alrovat>
<alrovat id = "5">
<mezo id = "hattol">20100112</mezo>
<mezo id = "tiszt">vezetõ tisztségviselõ (ügyvezetõ)</mezo>
<mezo id = "pnev">Barta Tivadar</mezo>
<mezo id = "panev">Zakar Anna</mezo>
<mezo id = "kepvo">x</mezo>
<mezo id = "jogvk">20100112</mezo>
<mezo id = "valtk">20100112</mezo>
<mezo id = "bkelt">20100126</mezo>
</alrovat>
</rovat>
<rovat id = "14">
<alrovat id = "3">
<mezo id = "hattol">20100112</mezo>
<mezo id = "cgjsz">0109069830</mezo>
<mezo id = "nev">AGO Könyvvizsgáló, Adó és Pénzügyi Tanácsadó Korlátolt Felelõsségû Társaság</mezo>
<mezo id = "orsz">HU</mezo>
<mezo id = "irsz">1124</mezo>
<mezo id = "hely">Budapest</mezo>
<mezo id = "teru">Hegyalja út 142.</mezo>
<mezo id = "pnev">Földi Gyula</mezo>
<mezo id = "panev">Domonkos Vincencia</mezo>
<mezo id = "jogvk">20100112</mezo>
<mezo id = "jogvv">20141231</mezo>
<mezo id = "valtk">20100112</mezo>
<mezo id = "bkelt">20100126</mezo>
</alrovat>
</rovat>
<rovat id = "20">
<alrovat id = "1">
<mezo id = "hattol">20010911</mezo>
<mezo id = "kshsz">10861617804211301</mezo>
</alrovat>
<alrovat id = "3">
<mezo id = "hattol">20080515</mezo>
<mezo id = "kshsz">10861617854111301</mezo>
<mezo id = "valtk">0</mezo>
<mezo id = "valtv">0</mezo>
<mezo id = "bkelt">20080515</mezo>
<mezo id = "tkelt">0</mezo>
</alrovat>
</rovat>
<rovat id = "21">
<alrovat id = "3">
<mezo id = "hattol">20081105</mezo>
<mezo id = "adosz">10861617242</mezo>
<mezo id = "fkdat">0</mezo>
<mezo id = "fmdat">0</mezo>
<mezo id = "jtdat">0</mezo>
<mezo id = "hmdat">0</mezo>
<mezo id = "hkdat">0</mezo>
<mezo id = "valtk">0</mezo>
<mezo id = "valtv">0</mezo>
<mezo id = "bkelt">20081105</mezo>
<mezo id = "tkelt">0</mezo>
</alrovat>
</rovat>
<rovat id = "0109">
<alrovat id = "4">
<mezo id = "hattol">19980702</mezo>
<mezo id = "befmert">30</mezo>
<mezo id = "pnev">Szabó Erika</mezo>
<mezo id = "pirsz">1201</mezo>
<mezo id = "phely">Budapest</mezo>
<mezo id = "pteru">Virág Benedek u.</mezo>
<mezo id = "phsz">12.</mezo>
</alrovat>
<alrovat id = "9">
<mezo id = "hattol">20080505</mezo>
<mezo id = "j">x</mezo>
<mezo id = "pnev">Barhács Anna</mezo>
<mezo id = "panev">Zakar Anna</mezo>
<mezo id = "pirsz">2600</mezo>
<mezo id = "phely">Vác, Kárász u. 29/B.</mezo>
<mezo id = "tagsk">19930817</mezo>
<mezo id = "tagsv">0</mezo>
<mezo id = "valtk">0</mezo>
<mezo id = "valtv">0</mezo>
<mezo id = "bkelt">20080505</mezo>
<mezo id = "tkelt">0</mezo>
</alrovat>
<alrovat id = "10">
<mezo id = "hattol">20080505</mezo>
<mezo id = "j">x</mezo>
<mezo id = "pnev">Németh Sándor</mezo>
<mezo id = "panev">Cseh Németh Mária</mezo>
<mezo id = "pirsz">2113</mezo>
<mezo id = "phely">Erdõkertes, Cseresznye fasor 20.</mezo>
<mezo id = "tagsk">19980702</mezo>
<mezo id = "tagsv">0</mezo>
<mezo id = "valtk">0</mezo>
<mezo id = "valtv">0</mezo>
<mezo id = "bkelt">20080505</mezo>
<mezo id = "tkelt">0</mezo>
</alrovat>
<alrovat id = "12">
<mezo id = "hattol">20090409</mezo>
<mezo id = "pnev">Barta Tivadar</mezo>
<mezo id = "panev">Zakar Anna</mezo>
<mezo id = "pirsz">2084</mezo>
<mezo id = "phely">Pilisszentiván, József A. utca 30.</mezo>
<mezo id = "tagsk">20090409</mezo>
<mezo id = "tagsv">0</mezo>
<mezo id = "valtk">20090409</mezo>
<mezo id = "valtv">0</mezo>
<mezo id = "bkelt">20090428</mezo>
<mezo id = "tkelt">0</mezo>
</alrovat>
</rovat>
<rovat id = "93">
<alrovat id = "1">
<mezo id = "cegallapot">0</mezo>
</alrovat>
</rovat>
<rovat id = "99">
<alrovat id = "0">
<mezo id = "hattol">0</mezo>
<mezo id = "hatig">0</mezo>
<mezo id = "szoveg">Németh Sándor 2113 Erdõkertes, Cseresznye fasor 20. sz. alatti lakos a Gazdasági társaságokról szóló 1997. évi CXLIV. tv. 292. § (1) bekezdésében foglalt kötelezettségének eleget téve bejelenti, hogy a Barhács és Társa Szervezési, Oktatási és Szolgáltató Korlátolt Felelõsségû Társaságban (1091 Budapest, Üllõi út 45.; Cg. [01 09 265923]) 1998. július 1-jén ajándékozás útján a szavazatok 30%-át megszerezte, ezzel jelentõs irányítást biztosító befolyással rendelkezik.<ujsor/>
</mezo>
<mezo id = "cjsz">0109265923</mezo>
<mezo id = "nev">Barhács és Társa Szervezési, Oktatási és Szolgáltató Kft.</mezo>
</alrovat>
<alrovat id = "1">
<mezo id = "hattol">0</mezo>
<mezo id = "hatig">0</mezo>
<mezo id = "szoveg">A bíróság a(z) 2000. 08. 21-én hozott végzését hivatalból az alábbiak szerint javítja (egészíti) ki:<ujsor/>
1(09). A társaság irányítását biztosító befolyásolás mértéke: 30.00000 %.<ujsor/>
 Szabó Erika<ujsor/>
1201 Budapest, Virág Benedek u. 12.<ujsor/>
 Törölve: 2000. 08. 21-i hatállyal.<ujsor/>
 Szabó Erika (an: Biczó Ilona)<ujsor/>
1201 Budapest, Virág Benedek u. 12.<ujsor/>
 Hatályos: 2000. 08. 21-tõl.<ujsor/>
Bejegyezve: 2001. 08. 09.<ujsor/>
</mezo>
<mezo id = "cjsz">0109265923</mezo>
<mezo id = "nev">Barhács és Társa Szervezési, Oktatási és Szolgáltató Kft.</mezo>
<mezo id = "cim">1091 Budapest, Üllõi út 45.</mezo>
<mezo id = "adosz">10861617243</mezo>
</alrovat>
<alrovat id = "2">
<mezo id = "hattol">0</mezo>
<mezo id = "hatig">0</mezo>
<mezo id = "szoveg">A bíróság a(z) 2001. 01. 15-én hozott végzését hivatalból az alábbiak szerint javítja (egészíti) ki:<ujsor/>
20. 10861617-8042-113-01.<ujsor/>
 Hatályos: 2001. 09. 11-tõl.<ujsor/>
32. 10100716-72254271-00000000<ujsor/>
 Budapest Bank Rt. EMKE Fiók (1072 Budapest, Rákóczi út 42.)<ujsor/>
 Hatályos: 1997. 11. 04-tõl.<ujsor/>
 10800100-50000000-03233022<ujsor/>
 CITIBANK Rt. ELC Fiók (1051 Budapest, Szabadság tér 7.)<ujsor/>
 Hatályos: 2001. 07. 02-tól.<ujsor/>
Bejegyezve: 2001. 09. 11.<ujsor/>
</mezo>
<mezo id = "cjsz">0109265923</mezo>
<mezo id = "nev">Barhács és Társa Szervezési, Oktatási és Szolgáltató Kft.</mezo>
<mezo id = "cim">1091 Budapest, Üllõi út 45.</mezo>
<mezo id = "adosz">10861617243</mezo>
</alrovat>
</rovat>
<rovat id = "99017">
<alrovat id = "1">
<mezo id = "kezd">20080101</mezo>
<mezo id = "veg">20081231</mezo>
<mezo id = "szorzo">1000</mezo>
<mezo id = "penz">HUF</mezo>
<mezo id = "a_eredm">103174</mezo>
<mezo id = "aktiv_el">0</mezo>
<mezo id = "eszk">0</mezo>
<mezo id = "celtart">0</mezo>
<mezo id = "netto">387535</mezo>
<mezo id = "forgo">0</mezo>
<mezo id = "kotelez">0</mezo>
<mezo id = "m_eredm">52539</mezo>
<mezo id = "passziv_el">0</mezo>
<mezo id = "toke">0</mezo>
<mezo id = "u_eredm">104431</mezo>
</alrovat>
<alrovat id = "2">
<mezo id = "kezd">20070101</mezo>
<mezo id = "veg">20071231</mezo>
<mezo id = "szorzo">1000</mezo>
<mezo id = "penz">HUF</mezo>
<mezo id = "a_eredm">25213</mezo>
<mezo id = "aktiv_el">0</mezo>
<mezo id = "eszk">17524</mezo>
<mezo id = "celtart">0</mezo>
<mezo id = "netto">211482</mezo>
<mezo id = "forgo">92450</mezo>
<mezo id = "kotelez">42592</mezo>
<mezo id = "m_eredm">21159</mezo>
<mezo id = "passziv_el">0</mezo>
<mezo id = "toke">67382</mezo>
<mezo id = "u_eredm">27015</mezo>
</alrovat>
<alrovat id = "3">
<mezo id = "kezd">20090101</mezo>
<mezo id = "veg">20091231</mezo>
<mezo id = "szorzo">1000</mezo>
<mezo id = "penz">HUF</mezo>
<mezo id = "a_eredm">-29143</mezo>
<mezo id = "aktiv_el">0</mezo>
<mezo id = "eszk">11717</mezo>
<mezo id = "celtart">0</mezo>
<mezo id = "netto">117816</mezo>
<mezo id = "forgo">132701</mezo>
<mezo id = "kotelez">53639</mezo>
<mezo id = "m_eredm">-29143</mezo>
<mezo id = "passziv_el">0</mezo>
<mezo id = "toke">90779</mezo>
<mezo id = "u_eredm">-29915</mezo>
</alrovat>
<alrovat id = "4">
<mezo id = "kezd">20100101</mezo>
<mezo id = "veg">20101231</mezo>
<mezo id = "szorzo">1000</mezo>
<mezo id = "penz">HUF</mezo>
<mezo id = "a_eredm">9904</mezo>
<mezo id = "aktiv_el">0</mezo>
<mezo id = "eszk">8108</mezo>
<mezo id = "celtart">0</mezo>
<mezo id = "netto">163575</mezo>
<mezo id = "forgo">93822</mezo>
<mezo id = "kotelez">31248</mezo>
<mezo id = "m_eredm">9904</mezo>
<mezo id = "passziv_el">0</mezo>
<mezo id = "toke">70682</mezo>
<mezo id = "u_eredm">11097</mezo>
</alrovat>
</rovat>
</ceg>
