<ceg id="0109690948">
<rovat id = "0">
<alrovat id = "1">
<mezo id = "bir">01</mezo>
<mezo id = "cf">09</mezo>
<mezo id = "szam">690948</mezo>
<mezo id = "nevalrovat">3</mezo>
<mezo id = "allapot">2</mezo>
<mezo id = "cim">1055 Budapest, Stollár Béla u. 22. 1. em. </mezo>
<mezo id = "plus">10</mezo>
<mezo id = "adosz">12528008241</mezo>
</alrovat>
</rovat>
<rovat id = "2">
<alrovat id = "3">
<mezo id = "hattol">20090710</mezo>
<mezo id = "nev">Axel N Films Filmkészítõ és Szolgáltató Korlátolt Felelõsségû Társaság &quot;felszámolás alatt&quot;</mezo>
<mezo id = "valtk">20090710</mezo>
<mezo id = "bkelt">20090713</mezo>
</alrovat>
</rovat>
<rovat id = "3">
<alrovat id = "3">
<mezo id = "hattol">20090710</mezo>
<mezo id = "nev">Axel N Films Kft. &quot;f.a.&quot;</mezo>
<mezo id = "valtk">20090710</mezo>
<mezo id = "bkelt">20090713</mezo>
</alrovat>
</rovat>
<rovat id = "4">
<alrovat id = "2">
<mezo id = "hattol">20081205</mezo>
<mezo id = "nev">Axel N Films Filproduction GmbH.</mezo>
<mezo id = "valtk">20081205</mezo>
<mezo id = "valtv">0</mezo>
<mezo id = "bkelt">20090105</mezo>
<mezo id = "tkelt">0</mezo>
</alrovat>
</rovat>
<rovat id = "5">
<alrovat id = "1">
<mezo id = "hattol">20000922</mezo>
<mezo id = "irsz">1055</mezo>
<mezo id = "hely">Budapest</mezo>
<mezo id = "teru">Stollár Béla u. 22. 1. em.</mezo>
</alrovat>
</rovat>
<rovat id = "8">
<alrovat id = "1">
<mezo id = "datum">20000906</mezo>
</alrovat>
<alrovat id = "2">
<mezo id = "datum">20050530</mezo>
</alrovat>
<alrovat id = "3">
<mezo id = "datum">20081205</mezo>
<mezo id = "valtk">0</mezo>
<mezo id = "valtv">0</mezo>
<mezo id = "bkelt">0</mezo>
<mezo id = "tkelt">0</mezo>
</alrovat>
</rovat>
<rovat id = "902">
<alrovat id = "6">
<mezo id = "hattol">20000922</mezo>
<mezo id = "tea08">5913</mezo>
</alrovat>
<alrovat id = "7">
<mezo id = "hattol">20050801</mezo>
<mezo id = "hengk1">0</mezo>
<mezo id = "hengv1">0</mezo>
<mezo id = "hengk2">0</mezo>
<mezo id = "hengv2">0</mezo>
<mezo id = "hengk3">0</mezo>
<mezo id = "hengv3">0</mezo>
<mezo id = "hengk4">0</mezo>
<mezo id = "hengv4">0</mezo>
<mezo id = "korlk">0</mezo>
<mezo id = "korlv">0</mezo>
<mezo id = "tea08">5914</mezo>
</alrovat>
<alrovat id = "12">
<mezo id = "hattol">20050801</mezo>
<mezo id = "hengk1">0</mezo>
<mezo id = "hengv1">0</mezo>
<mezo id = "hengk2">0</mezo>
<mezo id = "hengv2">0</mezo>
<mezo id = "hengk3">0</mezo>
<mezo id = "hengv3">0</mezo>
<mezo id = "hengk4">0</mezo>
<mezo id = "hengv4">0</mezo>
<mezo id = "korlk">0</mezo>
<mezo id = "korlv">0</mezo>
<mezo id = "tea08">7420</mezo>
</alrovat>
<alrovat id = "13">
<mezo id = "hattol">20050801</mezo>
<mezo id = "hengk1">0</mezo>
<mezo id = "hengv1">0</mezo>
<mezo id = "hengk2">0</mezo>
<mezo id = "hengv2">0</mezo>
<mezo id = "hengk3">0</mezo>
<mezo id = "hengv3">0</mezo>
<mezo id = "hengk4">0</mezo>
<mezo id = "hengv4">0</mezo>
<mezo id = "korlk">0</mezo>
<mezo id = "korlv">0</mezo>
<mezo id = "tea08">7320</mezo>
</alrovat>
<alrovat id = "18">
<mezo id = "hattol">20050801</mezo>
<mezo id = "hengk1">0</mezo>
<mezo id = "hengv1">0</mezo>
<mezo id = "hengk2">0</mezo>
<mezo id = "hengv2">0</mezo>
<mezo id = "hengk3">0</mezo>
<mezo id = "hengv3">0</mezo>
<mezo id = "hengk4">0</mezo>
<mezo id = "hengv4">0</mezo>
<mezo id = "korlk">0</mezo>
<mezo id = "korlv">0</mezo>
<mezo id = "tea08">6202</mezo>
</alrovat>
<alrovat id = "19">
<mezo id = "hattol">20050801</mezo>
<mezo id = "hengk1">0</mezo>
<mezo id = "hengv1">0</mezo>
<mezo id = "hengk2">0</mezo>
<mezo id = "hengv2">0</mezo>
<mezo id = "hengk3">0</mezo>
<mezo id = "hengv3">0</mezo>
<mezo id = "hengk4">0</mezo>
<mezo id = "hengv4">0</mezo>
<mezo id = "korlk">0</mezo>
<mezo id = "korlv">0</mezo>
<mezo id = "tea08">7739</mezo>
</alrovat>
<alrovat id = "20">
<mezo id = "hattol">20050801</mezo>
<mezo id = "hengk1">0</mezo>
<mezo id = "hengv1">0</mezo>
<mezo id = "hengk2">0</mezo>
<mezo id = "hengv2">0</mezo>
<mezo id = "hengk3">0</mezo>
<mezo id = "hengv3">0</mezo>
<mezo id = "hengk4">0</mezo>
<mezo id = "hengv4">0</mezo>
<mezo id = "korlk">0</mezo>
<mezo id = "korlv">0</mezo>
<mezo id = "tea08">7733</mezo>
</alrovat>
<alrovat id = "21">
<mezo id = "hattol">20050801</mezo>
<mezo id = "hengk1">0</mezo>
<mezo id = "hengv1">0</mezo>
<mezo id = "hengk2">0</mezo>
<mezo id = "hengv2">0</mezo>
<mezo id = "hengk3">0</mezo>
<mezo id = "hengv3">0</mezo>
<mezo id = "hengk4">0</mezo>
<mezo id = "hengv4">0</mezo>
<mezo id = "korlk">0</mezo>
<mezo id = "korlv">0</mezo>
<mezo id = "tea08">5813</mezo>
</alrovat>
<alrovat id = "22">
<mezo id = "hattol">20050801</mezo>
<mezo id = "hengk1">0</mezo>
<mezo id = "hengv1">0</mezo>
<mezo id = "hengk2">0</mezo>
<mezo id = "hengv2">0</mezo>
<mezo id = "hengk3">0</mezo>
<mezo id = "hengv3">0</mezo>
<mezo id = "hengk4">0</mezo>
<mezo id = "hengv4">0</mezo>
<mezo id = "korlk">0</mezo>
<mezo id = "korlv">0</mezo>
<mezo id = "tea08">5814</mezo>
</alrovat>
<alrovat id = "23">
<mezo id = "hattol">20050801</mezo>
<mezo id = "hengk1">0</mezo>
<mezo id = "hengv1">0</mezo>
<mezo id = "hengk2">0</mezo>
<mezo id = "hengv2">0</mezo>
<mezo id = "hengk3">0</mezo>
<mezo id = "hengv3">0</mezo>
<mezo id = "hengk4">0</mezo>
<mezo id = "hengv4">0</mezo>
<mezo id = "korlk">0</mezo>
<mezo id = "korlv">0</mezo>
<mezo id = "tea08">5920</mezo>
</alrovat>
<alrovat id = "24">
<mezo id = "hattol">20050801</mezo>
<mezo id = "hengk1">0</mezo>
<mezo id = "hengv1">0</mezo>
<mezo id = "hengk2">0</mezo>
<mezo id = "hengv2">0</mezo>
<mezo id = "hengk3">0</mezo>
<mezo id = "hengv3">0</mezo>
<mezo id = "hengk4">0</mezo>
<mezo id = "hengv4">0</mezo>
<mezo id = "korlk">0</mezo>
<mezo id = "korlv">0</mezo>
<mezo id = "tea08">1820</mezo>
</alrovat>
<alrovat id = "25">
<mezo id = "hattol">20050801</mezo>
<mezo id = "hengk1">0</mezo>
<mezo id = "hengv1">0</mezo>
<mezo id = "hengk2">0</mezo>
<mezo id = "hengv2">0</mezo>
<mezo id = "hengk3">0</mezo>
<mezo id = "hengv3">0</mezo>
<mezo id = "hengk4">0</mezo>
<mezo id = "hengv4">0</mezo>
<mezo id = "korlk">0</mezo>
<mezo id = "korlv">0</mezo>
<mezo id = "tea08">1820</mezo>
</alrovat>
<alrovat id = "26">
<mezo id = "hattol">20050801</mezo>
<mezo id = "hengk1">0</mezo>
<mezo id = "hengv1">0</mezo>
<mezo id = "hengk2">0</mezo>
<mezo id = "hengv2">0</mezo>
<mezo id = "hengk3">0</mezo>
<mezo id = "hengv3">0</mezo>
<mezo id = "hengk4">0</mezo>
<mezo id = "hengv4">0</mezo>
<mezo id = "korlk">0</mezo>
<mezo id = "korlv">0</mezo>
<mezo id = "tea08">1820</mezo>
</alrovat>
<alrovat id = "27">
<mezo id = "hattol">20050801</mezo>
<mezo id = "hengk1">0</mezo>
<mezo id = "hengv1">0</mezo>
<mezo id = "hengk2">0</mezo>
<mezo id = "hengv2">0</mezo>
<mezo id = "hengk3">0</mezo>
<mezo id = "hengv3">0</mezo>
<mezo id = "hengk4">0</mezo>
<mezo id = "hengv4">0</mezo>
<mezo id = "korlk">0</mezo>
<mezo id = "korlv">0</mezo>
<mezo id = "tea08">1820</mezo>
</alrovat>
<alrovat id = "28">
<mezo id = "hattol">20081205</mezo>
<mezo id = "fotev">x</mezo>
<mezo id = "hengk1">0</mezo>
<mezo id = "hengv1">0</mezo>
<mezo id = "hengk2">0</mezo>
<mezo id = "hengv2">0</mezo>
<mezo id = "hengk3">0</mezo>
<mezo id = "hengv3">0</mezo>
<mezo id = "hengk4">0</mezo>
<mezo id = "hengv4">0</mezo>
<mezo id = "korlk">0</mezo>
<mezo id = "korlv">0</mezo>
<mezo id = "valtk">20081205</mezo>
<mezo id = "valtv">0</mezo>
<mezo id = "bkelt">20090105</mezo>
<mezo id = "tkelt">0</mezo>
<mezo id = "tea08">5911</mezo>
</alrovat>
<alrovat id = "29">
<mezo id = "hattol">20081205</mezo>
<mezo id = "hengk1">0</mezo>
<mezo id = "hengv1">0</mezo>
<mezo id = "hengk2">0</mezo>
<mezo id = "hengv2">0</mezo>
<mezo id = "hengk3">0</mezo>
<mezo id = "hengv3">0</mezo>
<mezo id = "hengk4">0</mezo>
<mezo id = "hengv4">0</mezo>
<mezo id = "korlk">0</mezo>
<mezo id = "korlv">0</mezo>
<mezo id = "valtk">20081205</mezo>
<mezo id = "valtv">0</mezo>
<mezo id = "bkelt">20090105</mezo>
<mezo id = "tkelt">0</mezo>
<mezo id = "tea08">5811</mezo>
</alrovat>
<alrovat id = "30">
<mezo id = "hattol">20081205</mezo>
<mezo id = "hengk1">0</mezo>
<mezo id = "hengv1">0</mezo>
<mezo id = "hengk2">0</mezo>
<mezo id = "hengv2">0</mezo>
<mezo id = "hengk3">0</mezo>
<mezo id = "hengv3">0</mezo>
<mezo id = "hengk4">0</mezo>
<mezo id = "hengv4">0</mezo>
<mezo id = "korlk">0</mezo>
<mezo id = "korlv">0</mezo>
<mezo id = "valtk">20081205</mezo>
<mezo id = "valtv">0</mezo>
<mezo id = "bkelt">20090105</mezo>
<mezo id = "tkelt">0</mezo>
<mezo id = "tea08">6209</mezo>
</alrovat>
<alrovat id = "31">
<mezo id = "hattol">20081205</mezo>
<mezo id = "hengk1">0</mezo>
<mezo id = "hengv1">0</mezo>
<mezo id = "hengk2">0</mezo>
<mezo id = "hengv2">0</mezo>
<mezo id = "hengk3">0</mezo>
<mezo id = "hengv3">0</mezo>
<mezo id = "hengk4">0</mezo>
<mezo id = "hengv4">0</mezo>
<mezo id = "korlk">0</mezo>
<mezo id = "korlv">0</mezo>
<mezo id = "valtk">20081205</mezo>
<mezo id = "valtv">0</mezo>
<mezo id = "bkelt">20090105</mezo>
<mezo id = "tkelt">0</mezo>
<mezo id = "tea08">6311</mezo>
</alrovat>
<alrovat id = "32">
<mezo id = "hattol">20081205</mezo>
<mezo id = "hengk1">0</mezo>
<mezo id = "hengv1">0</mezo>
<mezo id = "hengk2">0</mezo>
<mezo id = "hengv2">0</mezo>
<mezo id = "hengk3">0</mezo>
<mezo id = "hengv3">0</mezo>
<mezo id = "hengk4">0</mezo>
<mezo id = "hengv4">0</mezo>
<mezo id = "korlk">0</mezo>
<mezo id = "korlv">0</mezo>
<mezo id = "valtk">20081205</mezo>
<mezo id = "valtv">0</mezo>
<mezo id = "bkelt">20090105</mezo>
<mezo id = "tkelt">0</mezo>
<mezo id = "tea08">6312</mezo>
</alrovat>
<alrovat id = "33">
<mezo id = "hattol">20081205</mezo>
<mezo id = "hengk1">0</mezo>
<mezo id = "hengv1">0</mezo>
<mezo id = "hengk2">0</mezo>
<mezo id = "hengv2">0</mezo>
<mezo id = "hengk3">0</mezo>
<mezo id = "hengv3">0</mezo>
<mezo id = "hengk4">0</mezo>
<mezo id = "hengv4">0</mezo>
<mezo id = "korlk">0</mezo>
<mezo id = "korlv">0</mezo>
<mezo id = "valtk">20081205</mezo>
<mezo id = "valtv">0</mezo>
<mezo id = "bkelt">20090105</mezo>
<mezo id = "tkelt">0</mezo>
<mezo id = "tea08">7022</mezo>
</alrovat>
<alrovat id = "34">
<mezo id = "hattol">20081205</mezo>
<mezo id = "hengk1">0</mezo>
<mezo id = "hengv1">0</mezo>
<mezo id = "hengk2">0</mezo>
<mezo id = "hengv2">0</mezo>
<mezo id = "hengk3">0</mezo>
<mezo id = "hengv3">0</mezo>
<mezo id = "hengk4">0</mezo>
<mezo id = "hengv4">0</mezo>
<mezo id = "korlk">0</mezo>
<mezo id = "korlv">0</mezo>
<mezo id = "valtk">20081205</mezo>
<mezo id = "valtv">0</mezo>
<mezo id = "bkelt">20090105</mezo>
<mezo id = "tkelt">0</mezo>
<mezo id = "tea08">7311</mezo>
</alrovat>
<alrovat id = "35">
<mezo id = "hattol">20081205</mezo>
<mezo id = "hengk1">0</mezo>
<mezo id = "hengv1">0</mezo>
<mezo id = "hengk2">0</mezo>
<mezo id = "hengv2">0</mezo>
<mezo id = "hengk3">0</mezo>
<mezo id = "hengv3">0</mezo>
<mezo id = "hengk4">0</mezo>
<mezo id = "hengv4">0</mezo>
<mezo id = "korlk">0</mezo>
<mezo id = "korlv">0</mezo>
<mezo id = "valtk">20081205</mezo>
<mezo id = "valtv">0</mezo>
<mezo id = "bkelt">20090105</mezo>
<mezo id = "tkelt">0</mezo>
<mezo id = "tea08">7430</mezo>
</alrovat>
<alrovat id = "36">
<mezo id = "hattol">20081205</mezo>
<mezo id = "hengk1">0</mezo>
<mezo id = "hengv1">0</mezo>
<mezo id = "hengk2">0</mezo>
<mezo id = "hengv2">0</mezo>
<mezo id = "hengk3">0</mezo>
<mezo id = "hengv3">0</mezo>
<mezo id = "hengk4">0</mezo>
<mezo id = "hengv4">0</mezo>
<mezo id = "korlk">0</mezo>
<mezo id = "korlv">0</mezo>
<mezo id = "valtk">20081205</mezo>
<mezo id = "valtv">0</mezo>
<mezo id = "bkelt">20090105</mezo>
<mezo id = "tkelt">0</mezo>
<mezo id = "tea08">8299</mezo>
</alrovat>
<alrovat id = "37">
<mezo id = "hattol">20081205</mezo>
<mezo id = "hengk1">0</mezo>
<mezo id = "hengv1">0</mezo>
<mezo id = "hengk2">0</mezo>
<mezo id = "hengv2">0</mezo>
<mezo id = "hengk3">0</mezo>
<mezo id = "hengv3">0</mezo>
<mezo id = "hengk4">0</mezo>
<mezo id = "hengv4">0</mezo>
<mezo id = "korlk">0</mezo>
<mezo id = "korlv">0</mezo>
<mezo id = "valtk">20081205</mezo>
<mezo id = "valtv">0</mezo>
<mezo id = "bkelt">20090105</mezo>
<mezo id = "tkelt">0</mezo>
<mezo id = "tea08">9003</mezo>
</alrovat>
<alrovat id = "38">
<mezo id = "hattol">20081205</mezo>
<mezo id = "hengk1">0</mezo>
<mezo id = "hengv1">0</mezo>
<mezo id = "hengk2">0</mezo>
<mezo id = "hengv2">0</mezo>
<mezo id = "hengk3">0</mezo>
<mezo id = "hengv3">0</mezo>
<mezo id = "hengk4">0</mezo>
<mezo id = "hengv4">0</mezo>
<mezo id = "korlk">0</mezo>
<mezo id = "korlv">0</mezo>
<mezo id = "valtk">20081205</mezo>
<mezo id = "valtv">0</mezo>
<mezo id = "bkelt">20090105</mezo>
<mezo id = "tkelt">0</mezo>
<mezo id = "tea08">9329</mezo>
</alrovat>
</rovat>
<rovat id = "11">
<alrovat id = "2">
<mezo id = "hattol">20050801</mezo>
<mezo id = "kp">32490000</mezo>
<mezo id = "app">0</mezo>
<mezo id = "szam">32490000</mezo>
<mezo id = "penz">Ft</mezo>
</alrovat>
</rovat>
<rovat id = "13">
<alrovat id = "4">
<mezo id = "hattol">20090710</mezo>
<mezo id = "nev">PARA Gazdasági Tanácsadó Kft.</mezo>
<mezo id = "irsz">1138</mezo>
<mezo id = "hely">Budapest</mezo>
<mezo id = "teru">Népfürdõ u. 7.</mezo>
<mezo id = "tiszt">felszámolóbiztos</mezo>
<mezo id = "pnev">dr. Pallos Dénes</mezo>
<mezo id = "panev">Vajta Erzsébet</mezo>
<mezo id = "pirsz">1138</mezo>
<mezo id = "phely">Budapest</mezo>
<mezo id = "pteru">Népfürdõ u. 7.</mezo>
<mezo id = "kepvo">x</mezo>
<mezo id = "jogvk">20090710</mezo>
<mezo id = "valtk">20090710</mezo>
<mezo id = "bkelt">20090721</mezo>
</alrovat>
</rovat>
<rovat id = "14">
<alrovat id = "2">
<mezo id = "hattol">20081205</mezo>
<mezo id = "cgjsz">109267325</mezo>
<mezo id = "nev">&quot;Ráta &apos;80&quot; Szolgáltató Korlátolt Felelõsségû Társaság</mezo>
<mezo id = "irsz">1221</mezo>
<mezo id = "hely">Budapest, Gerinc u. 80.</mezo>
<mezo id = "pnev">Feinné Kaszab Sarolta</mezo>
<mezo id = "panev">Nagy Sarolta</mezo>
<mezo id = "pirsz">1221</mezo>
<mezo id = "phely">Budapest, Gerinc u. 80.</mezo>
<mezo id = "jogvk">20081209</mezo>
<mezo id = "jogvv">20131209</mezo>
<mezo id = "valtk">20081205</mezo>
<mezo id = "valtv">0</mezo>
<mezo id = "bkelt">20090105</mezo>
<mezo id = "tkelt">0</mezo>
</alrovat>
</rovat>
<rovat id = "20">
<alrovat id = "1">
<mezo id = "hattol">20000922</mezo>
<mezo id = "kshsz">12528008921111301</mezo>
</alrovat>
</rovat>
<rovat id = "21">
<alrovat id = "2">
<mezo id = "hattol">20040304</mezo>
<mezo id = "adosz">12528008241</mezo>
<mezo id = "kadosz">HU12528008</mezo>
<mezo id = "nydat">20040501</mezo>
</alrovat>
</rovat>
<rovat id = "28">
<alrovat id = "1">
<mezo id = "hattol">20090710</mezo>
<mezo id = "felszk">20090710</mezo>
<mezo id = "valtk">20090710</mezo>
<mezo id = "bkelt">20090713</mezo>
</alrovat>
</rovat>
<rovat id = "0109">
<alrovat id = "1">
<mezo id = "hattol">20000922</mezo>
<mezo id = "pnev">Alexander Nemetz</mezo>
<mezo id = "panev">Herta Nemetz</mezo>
<mezo id = "pkorsz">AT</mezo>
<mezo id = "pkirsz">1060</mezo>
<mezo id = "pkhely">Wien, Hofmühlgasse 7.</mezo>
<mezo id = "pmnev">Dr. Hámori Ágnes</mezo>
<mezo id = "pmanev">Nagy Ágnes</mezo>
<mezo id = "pmirsz">1028</mezo>
<mezo id = "pmhely">Budapest, Járóka u. 10/A.</mezo>
</alrovat>
</rovat>
<rovat id = "93">
<alrovat id = "1">
<mezo id = "cegallapot">2</mezo>
</alrovat>
</rovat>
<rovat id = "99">
<alrovat id = "0">
<mezo id = "hattol">0</mezo>
<mezo id = "hatig">0</mezo>
<mezo id = "szoveg">A Fõvárosi Bíróság<ujsor/>
32.Fpk.01-09-002119/7. sz. végzése<ujsor/>
felszámolás megindításának közzétételérõl<ujsor/>
A bíróság elrendeli annak a Cégközlönyben való közzétételét, hogy a(z)<ujsor/>
2009. május 27. napján jogerõre emelkedett végzésével a(z) Axel N Films<ujsor/>
Filmkészítõ és Szolgáltató Korlátolt Felelõsségû Társaság (1055 Budapest,<ujsor/>
Stollár Béla u 22. 1. em.; cégjegyzékszáma: 01 09 690948; adószáma:<ujsor/>
12528008-2-41) adós felszámolását fõeljárásként elrendelte.<ujsor/>
A bíróság által kijelölt felszámoló:<ujsor/>
PARA Gazdasági Tanácsadó Kft., 1138 Budapest, Népfürdõ u. 7.<ujsor/>
A felszámolóbiztos(ok):<ujsor/>
dr. Pallos Dénes 1138 Budapest, Népfürdõ u. 7.<ujsor/>
A felszámolási eljárás megindítására irányuló kérelem benyújtásának<ujsor/>
idõpontja: 2009. március 20.<ujsor/>
A felszámolás kezdõ idõpontja e végzés Cégközlönyben való közzétételének<ujsor/>
napja.<ujsor/>
A társaság tagja: Alexander Nemetz (an: Herta Hemetz) AT 1060 Wien, Hofmühl<ujsor/>
gasse 7. Kézbesítési megbízott: Dr. Hámori Ágnes (an: Nagy ágnes) 1028<ujsor/>
Budapest, Járóka u. 10/A.<ujsor/>
A Fõvárosi Bíróság Gazdasági Hivatalánál kezelt elkülönített számla száma:<ujsor/>
10032000-01483013-24000004.<ujsor/>
Mindazok, akik az adóssal szemben fennálló követeléseiket a felszámolás<ujsor/>
során hitelezõként érvényesíteni kívánják, ismert követeléseiket e végzés<ujsor/>
közzétételétõl számított 40 napon belül jelentsék be a felszámolónak.<ujsor/>
A felszámoló - a módosított 1991. évi XLIX. tv. 57. § (1) bekezdés a) és c)<ujsor/>
pontjában meghatározott követelések kivételével - csak azt a bejelentést<ujsor/>
veszi nyilvántartásba, amely után az igénybejelentõ a követelés 1 %-át, de<ujsor/>
legalább 1.000 Ft-ot, legfeljebb 100.000 Ft-ot az e végzésben megjelölt<ujsor/>
számlára - a bírósági ügyszámra (végzés számra) hivatkozással - 40<ujsor/>
napon belül befizetett és ezt a felszámoló részére igazolta.<ujsor/>
Budapest, 2009. június 30.<ujsor/>
A közzététel idõpontja: 2009. július 10.<ujsor/>
</mezo>
<mezo id = "cjsz">0109690948</mezo>
<mezo id = "nev">Axel N Films Filmkészítõ és Szolgáltató Korlátolt Felelõsségû Társaság</mezo>
<mezo id = "adosz">12528008241</mezo>
</alrovat>
<alrovat id = "1">
<mezo id = "hattol">0</mezo>
<mezo id = "hatig">0</mezo>
<mezo id = "szoveg">A REDDITUM Gazdasági Tanácsadó Korlátolt Felelõsségû Társaság (Cg.: [01 09 710659]; székhely: 1051 Budapest, Nádor u. 15.; korábban: PARA Gazdasági Tanácsadó Kft.), Fõvárosi Bíróság 32. Fpk. 01-09-002119/3. számú végzésével kijelölt Axel N Films Filmkészítõ és Szolgáltató Kft. „f. a.” (Cg.: [01 09 690948]; székhelye: 1055 Budapest, Stollár Béla u. 22. I. em.) felszámolójaként<ujsor/>
nyilvános pályázat<ujsor/>
útján kívánja értékesíteni a társaság tulajdonában álló, külön listában feltüntetett, használt irodai felszereléseket és egyéb tárgyi eszközöket.<ujsor/>
Az értékesítendõ ingóságok irányára: 1 000 000 Ft + áfa (egymillió forint + áfa).<ujsor/>
Érvényes ajánlat feltétele:<ujsor/>
­ az irányár 20%-ának bánatpénzként történõ befizetése az Axel N Films Kft. „f. a.” Magyarországi Volksbank Zrt.-nél vezetett 14100017-15968349-01000002 számú bankszámlájára „AXEL N Films Kft. bánatpénz” megjelöléssel, valamint ennek igazolása a benyújtási határidõig [a pénzügyi teljesítés (terhelés) pályázathoz történõ csatolásával],<ujsor/>
­ 60 napos ajánlati kötöttség vállalása.<ujsor/>
A felszámoló az értékesítéssel kapcsolatban írásos vételi ajánlatokat kér benyújtani a REDDITUM Gazdasági Tanácsadó Kft. (1051 Budapest, Nádor u. 15.) címére kizárólag postai úton „Axel N Films Kft. f. a. vételi ajánlat” megjelöléssel. Az ajánlatokat kettõs, zárt borítékban kérjük feladni. A belsõ borítékon az „Axel N Films Kft. f. a. vételi ajánlat” megjelölésen kívül más adat nem szerepelhet.<ujsor/>
Az ajánlatok benyújtásának idõpontja: legkésõbb a jelen hirdetmény Cégközlönyben való közzétételtõl számított 15. nap 24 óráig.<ujsor/>
A pályázattal kapcsolatosan további információ dr. Pallos Dénes felszámolóbiztostól a 450-0737-es telefonszámon kérhetõ.<ujsor/>
Az ajánlatok bontására a benyújtási határidõt követõ 8 napon belül, közjegyzõ jelenlétében kerül sor. A benyújtási határidõt követõ 15 napon belül a felszámoló az ajánlatokat értékeli. Az értékelés eredményérõl jegyzõkönyv készül, melyet bármely hitelezõ megtekinthet. Az ajánlatok elbírálása eredményérõl a felszámoló az érdekelteket írásban értesíti.<ujsor/>
A felszámoló a pályázatot megfelelõ ajánlat hiányában eredménytelennek nyilvánítja, és új pályázatot írhat ki. A pályázati ajánlatokat a felszámoló az árajánlatok nagysága alapján bírálja el.<ujsor/>
Amennyiben érkezik több megfelelõ ajánlat, és a legjobb ajánlati árat követõ ajánlati ár a legmagasabb ajánlati ár 90%-át eléri, a felszámoló a pályázók között nyilvános ártárgyalást tart. Az ártárgyalásra a felszámoló azokat az ajánlattevõket hívja meg, akiknek az ajánlati ára a legmagasabb ajánlati ár 90%-át elérte. Az ártárgyalás esetén a felszámoló az elõvásárlási szándékukat írásban bejelentõ elõvásárlásra jogosultakat konkrét nyilatkozattételre meghívja.<ujsor/>
A felszámolási eljárásra az 1997. évi XXVII. törvénnyel módosított 1991. évi IL. törvény rendelkezései az irányadók.<ujsor/>
Az elõvásárlási jogosultak e jogukat a nyilvános értékesítés keretein belül gyakorolhatják.<ujsor/>
A felszámoló felhívja az elõvásárlásra jogosultakat arra, hogy amennyiben a pályázat benyújtásának határidejéig az elõvásárlási jog gyakorlására irányuló szándékukat írásban nem jelentik be, a felszámoló úgy tekinti, hogy ezen elõvásárlási jogukkal élni nem kívánnak.<ujsor/>
</mezo>
<mezo id = "cjsz">0109690948</mezo>
<mezo id = "nev">Axel N Films Filmkészítõ és Szolgáltató Korlátolt Felelõsségû Társaság &quot;felszámolás alatt&quot;</mezo>
<mezo id = "cim">1055 Budapest</mezo>
</alrovat>
<alrovat id = "2">
<mezo id = "hattol">0</mezo>
<mezo id = "hatig">0</mezo>
<mezo id = "szoveg">A PARA Gazdasági Tanácsadó Korlátolt Felelõsségû Társaság (Cg.: [01 09 710659]; 1138 Budapest, Népfürdõ u. 7.; korábban: REDDITUM Gazdasági Tanácsadó Kft.) mint a Fõvárosi Bíróság 32. Fpk. 01-09-002119/3. számú végzésével kijelölt, az Axel N Films Filmkészítõ és Szolgáltató Kft. „f. a.” (Cg.: [01 09 690948]; 1055 Budapest, Stollár Béla u. 22. I. em.) felszámolója<ujsor/>
nyilvános pályázat<ujsor/>
útján kívánja értékesíteni a társaság tulajdonában álló, alábbiakban feltüntetett, használt irodai felszereléseket és egyéb tárgyi eszközöket.<ujsor/>
Megnevezés Darab Megjegyzés<ujsor/>
Gurulós kisszekrény 1<ujsor/>
HP Laserjet 1016 1<ujsor/>
Fém gurulós polc 1<ujsor/>
Filccel írható tábla 1 180 × 90 cm<ujsor/>
Parafás hirdetõtábla 1 120 × 90 cm<ujsor/>
Asztal kiegészítõkkel<ujsor/>
Tûzoltó készülék 1 Porral oltó, 6 kg<ujsor/>
Forgós szék 4<ujsor/>
Falikép 1<ujsor/>
Üzenõfal 1 60 × 40 cm<ujsor/>
Ufesa FD 82041T ventilátor 1 60 W<ujsor/>
Fehér polc 2<ujsor/>
Szürke-fekete kockás szék 4<ujsor/>
Fekete-szürke kockás szék 2<ujsor/>
Szürke polc (masszív) 3<ujsor/>
Bosch hûtõ 1 DG125E11RAW5R600a, 701 Rw<ujsor/>
Számítógépasztal 1<ujsor/>
Kék szék 3<ujsor/>
Dohányzóasztal 1<ujsor/>
Parafa üzenõtábla 2<ujsor/>
Zárható háromfiókos gurulós szekrény 2<ujsor/>
V.-kék kistányér 2<ujsor/>
V.-kék lapostányér 2<ujsor/>
S.-kék kistányér 2<ujsor/>
Kkék kistányér 3<ujsor/>
Kék lapostányér 6<ujsor/>
V.-kék pizzástányér 2<ujsor/>
Vágódeszka 1<ujsor/>
S.-kék lapostányér 2<ujsor/>
Kávéscsésze alátétekkel<ujsor/>
Hamutál 1<ujsor/>
Fehér lapostányér 1<ujsor/>
Mélytányér (Luminarc) 2<ujsor/>
Lapostányér (Luminarc) 1<ujsor/>
Kék-szürke termosz 1<ujsor/>
Hagyományos kávéfõzõ 1<ujsor/>
IMAC személyi számítógép 1 (billentyûzet, egér, hangszóró)<ujsor/>
800 MHz/256MB/60HQ<ujsor/>
SeverinArt.SA927S szendvics sütõ 1 230 V, 50 Hz, 700 W<ujsor/>
Használt tonerek 5 HP Q6002A-Q6000A-Q2612A,<ujsor/>
Restart 12AR 2 db<ujsor/>
Asztallapok különbözõ méretben 20<ujsor/>
Sima asztallap 14<ujsor/>
Asztallábtartóval 2<ujsor/>
T alakú asztalláb 1<ujsor/>
Egy rekesz asztallábtakaró<ujsor/>
Fehér asztalláb 9<ujsor/>
Szürke asztalláb 3<ujsor/>
Szürke polc 4<ujsor/>
Lexmark Z612 1<ujsor/>
HP Deskjet 5550 1<ujsor/>
HP 970 Cxi Deskjet 1<ujsor/>
Esselte kihúzható irattartó 2<ujsor/>
Take it irattartó 13<ujsor/>
Noname irattartó 1<ujsor/>
Polaroid 600 fényképezõgép 1<ujsor/>
CD-tartó 2<ujsor/>
IBICO COMBMAN lefûzõ 1<ujsor/>
DVD Studio Pro 3 1<ujsor/>
Final Cut Studio Pro 3 1<ujsor/>
Ikeás müzlistányér 4<ujsor/>
Hamutartó 1<ujsor/>
Kis tejeskiöntõ 1<ujsor/>
Barna müzlistányér 3<ujsor/>
Kék cifrás mélytányér 6<ujsor/>
Ikeás kék kistányér 3<ujsor/>
Mélytányér 2<ujsor/>
V.-kék-fehér csíkos lapostányér (IKEA) 2<ujsor/>
V.-kék-fehér csíkos pizzástányér (IKEA) 2<ujsor/>
Kék pizzástányér (IKEA) 2<ujsor/>
S.-kék csíkos pizzástányér (IKEA) 2<ujsor/>
Kék lapostányér (IKEA) 1<ujsor/>
Telefunken PAL COLOR SX 290 TV 1 RCA, Scart csatlakozás, 70 cm átmérõ<ujsor/>
Orion T20MS Tv 1 RCA bemenet, távirányító<ujsor/>
Dreher 0,3 l-es pohár 11<ujsor/>
Apollo electronics WINNER 1000 iratmegsemmisítõ 1<ujsor/>
Technolux erõsítõ 1<ujsor/>
Siemens XPRESS LINK 1<ujsor/>
WLAN kábelek több db<ujsor/>
Canon Cartridge H GP 160 series 1<ujsor/>
Salton calad XPRESS 1<ujsor/>
HP Laserjet 96A (2100-2200 series) 1<ujsor/>
Adobe Creative Suite Standard 1<ujsor/>
TDK Professional Diac PD­RE23CV 1 23 GB<ujsor/>
Seagate Barracuda ATAIV 1 80 GB<ujsor/>
Sony BCT-5Ma Betacam SP 1<ujsor/>
Daewoo DV44D videomagnó 1 4 fejes, JET DRIVE + távirányító<ujsor/>
Final Cut Pro HD 1<ujsor/>
Final Cut Pro 3 1<ujsor/>
Upper LI5­API­800 PYRO 1394 Drive Kit 1 ADS technologies<ujsor/>
Siemens S30817 vezetékes telefon 4<ujsor/>
Siemens BAKOM 96.0012T.P. 7 meg 8 db kábel<ujsor/>
Nile hordozható hûtõ-fûtõ ventilátor 2 2200 W<ujsor/>
D­Link ADSL modem (DSL­360R) 1 kábelek<ujsor/>
Canon GP 160F másoló 1 gurulós állvány és tartozékok<ujsor/>
Sony KV­21T3K televízió 1 scart és koax csatlakozás 50 Hz, 51 cm átmérõ<ujsor/>
Sony SLV­SE500K videomagnó 1 távirányító és használati utasítás<ujsor/>
Videoton Ts 2120 OSD 1 50 Hz, 51 cm, táv.<ujsor/>
Hûtõtáska, 24 l 2 egyik sérült<ujsor/>
Hûtõtáska, 15 l 1<ujsor/>
Rowenta Allegro Espresso ES 050 1 750 W<ujsor/>
Braun vízmelegítõ 1 hiányzik az alja<ujsor/>
Moulinex Cocoon Aroma guide AR4 1 650 W<ujsor/>
Lival Shuttle Plus 1 Mpx. 24 W<ujsor/>
Sony Digital Photo Printer DP­SV 88 1 használati utasítás, távirányító, kábelek<ujsor/>
Az értékesítendõ ingóságok irányára: 1 000 000 Ft + áfa (egymillió forint + áfa).<ujsor/>
Érvényes ajánlat feltétele:<ujsor/>
­ az irányár 20%-ának bánatpénzként történõ befizetése az Axel N Films Kft. „f. a.” Magyarországi Volksbank Zrt.-nél vezetett 14100017-15968349-01000002 számú bankszámlájára „Axel N Films Kft. bánatpénz” megjelöléssel, valamint ennek igazolása a benyújtási határidõig [a pénzügyi teljesítés (terhelés) pályázathoz történõ csatolásával],<ujsor/>
­ 60 napos ajánlati kötöttség vállalása.<ujsor/>
A felszámoló az értékesítéssel kapcsolatban írásos vételi ajánlatokat kér benyújtani a PARA Gazdasági Tanácsadó Kft. 1138 Budapest, Népfürdõ u. 7. szám alatti címére kizárólag postai úton „Axel N Films Kft. f. a. vételi ajánlat” megjelöléssel. Az ajánlatokat kettõs, zárt borítékban kérjük feladni. A belsõ borítékon az „Axel N Films Kft. f. a. vételi ajánlat” megjelölésen kívül más adat nem szerepelhet.<ujsor/>
Az ajánlatok benyújtásának idõpontja: legkésõbb a jelen hirdetmény Cégközlönyben való közzétételétõl számított 15. nap 24 óráig.<ujsor/>
A pályázattal kapcsolatosan további információ dr. Pallos Dénes felszámolóbiztostól a 06 (1) 450-0737-es telefonszámon kérhetõ.<ujsor/>
Az ajánlatok bontására a benyújtási határidõt követõ 8 napon belül, közjegyzõ jelenlétében kerül sor. A benyújtási határidõt követõ 15 napon belül a felszámoló az ajánlatokat értékeli. Az értékelés eredményérõl jegyzõkönyv készül, melyet bármely hitelezõ megtekinthet. Az ajánlatok elbírálása eredményérõl a felszámoló az érdekelteket írásban értesíti.<ujsor/>
A felszámoló a pályázatot megfelelõ ajánlat hiányában eredménytelennek nyilvánítja, és új pályázatot írhat ki. A pályázati ajánlatokat a felszámoló az árajánlatok nagysága alapján bírálja el.<ujsor/>
Amennyiben érkezik megfelelõ ajánlat, de a legjobb ajánlati árat követõ ajánlati ár a legmagasabb ajánlati ár 90%-át eléri, a felszámoló a pályázók között nyilvános ártárgyalást tart. Az ártárgyalásra a felszámoló azokat az ajánlattevõket hívja meg, akiknek az ajánlati ára a legmagasabb ajánlati ár 90%-át elérte. Az ártárgyalás esetén a felszámoló az elõvásárlási szándékukat írásban bejelentõ elõvásárlásra jogosultakat konkrét nyilatkozattételre meghívja.<ujsor/>
A felszámolási eljárásra az 1997. évi XXVII. törvénnyel módosított 1991. évi IL. törvény rendelkezései az irányadóak.<ujsor/>
Az elõvásárlási jogosultak e jogukat a nyilvános értékesítés keretein belül gyakorolhatják.<ujsor/>
A felszámoló felhívja az elõvásárlásra jogosultakat arra, hogy amennyiben a pályázat benyújtásának határidejéig az elõvásárlási jog gyakorlására irányuló szándékukat írásban nem jelentik be, a felszámoló úgy tekinti, hogy ezen elõvásárlási jogukkal élni nem kívánnak.<ujsor/>
</mezo>
<mezo id = "cjsz">0109690948</mezo>
<mezo id = "nev">Axel N Films Filmkészítõ és Szolgáltató Korlátolt Felelõsségû Társaság &quot;felszámolás alatt&quot;</mezo>
<mezo id = "cim">1055 Budapest</mezo>
</alrovat>
</rovat>
<rovat id = "99017">
<alrovat id = "1">
<mezo id = "kezd">20080101</mezo>
<mezo id = "veg">20081231</mezo>
<mezo id = "szorzo">1000</mezo>
<mezo id = "penz">HUF</mezo>
<mezo id = "a_eredm">-25691</mezo>
<mezo id = "aktiv_el">607</mezo>
<mezo id = "eszk">506</mezo>
<mezo id = "celtart">0</mezo>
<mezo id = "netto">135500</mezo>
<mezo id = "forgo">9202</mezo>
<mezo id = "kotelez">22953</mezo>
<mezo id = "m_eredm">-25691</mezo>
<mezo id = "passziv_el">58</mezo>
<mezo id = "toke">-12696</mezo>
<mezo id = "u_eredm">-35613</mezo>
</alrovat>
<alrovat id = "2">
<mezo id = "kezd">20090101</mezo>
<mezo id = "veg">20090708</mezo>
<mezo id = "szorzo">1000</mezo>
<mezo id = "penz">HUF</mezo>
<mezo id = "a_eredm">1120</mezo>
<mezo id = "aktiv_el">0</mezo>
<mezo id = "eszk">274</mezo>
<mezo id = "celtart">0</mezo>
<mezo id = "netto">70</mezo>
<mezo id = "forgo">5372</mezo>
<mezo id = "kotelez">17288</mezo>
<mezo id = "m_eredm">1055</mezo>
<mezo id = "passziv_el">0</mezo>
<mezo id = "toke">-11642</mezo>
<mezo id = "u_eredm">-4035</mezo>
</alrovat>
<alrovat id = "3">
<mezo id = "kezd">20070101</mezo>
<mezo id = "veg">20071231</mezo>
<mezo id = "szorzo">1000</mezo>
<mezo id = "penz">HUF</mezo>
<mezo id = "a_eredm">231</mezo>
<mezo id = "aktiv_el">2647</mezo>
<mezo id = "eszk">8361</mezo>
<mezo id = "celtart">0</mezo>
<mezo id = "netto">391606</mezo>
<mezo id = "forgo">50727</mezo>
<mezo id = "kotelez">48063</mezo>
<mezo id = "m_eredm">140</mezo>
<mezo id = "passziv_el">768</mezo>
<mezo id = "toke">12904</mezo>
<mezo id = "u_eredm">2653</mezo>
</alrovat>
</rovat>
</ceg>
